{"sentences":[{"index":0,"tokens":[{"index":1,"word":"From","originalText":"From","lemma":"from","characterOffsetBegin":0,"characterOffsetEnd":4,"pos":"IN","before":"","after":""},{"index":2,"word":":","originalText":":","lemma":":","characterOffsetBegin":4,"characterOffsetEnd":5,"pos":":","before":"","after":" "},{"index":3,"word":"henry@zoo.toronto.edu","originalText":"henry@zoo.toronto.edu","lemma":"henry@zoo.toronto.edu","characterOffsetBegin":6,"characterOffsetEnd":27,"pos":"NN","before":" ","after":" "},{"index":4,"word":"-LRB-","originalText":"(","lemma":"-lrb-","characterOffsetBegin":28,"characterOffsetEnd":29,"pos":"-LRB-","before":" ","after":""},{"index":5,"word":"Henry","originalText":"Henry","lemma":"Henry","characterOffsetBegin":29,"characterOffsetEnd":34,"pos":"NNP","before":"","after":" "},{"index":6,"word":"Spencer","originalText":"Spencer","lemma":"Spencer","characterOffsetBegin":35,"characterOffsetEnd":42,"pos":"NNP","before":" ","after":""},{"index":7,"word":"-RRB-","originalText":")","lemma":"-rrb-","characterOffsetBegin":42,"characterOffsetEnd":43,"pos":"-RRB-","before":"","after":""}]}]}
{"sentences":[{"index":0,"tokens":[{"index":1,"word":"Subject","originalText":"Subject","lemma":"Subject","characterOffsetBegin":0,"characterOffsetEnd":7,"pos":"NNP","before":"","after":""},{"index":2,"word":":","originalText":":","lemma":":","characterOffsetBegin":7,"characterOffsetEnd":8,"pos":":","before":"","after":" "},{"index":3,"word":"Re","originalText":"Re","lemma":"Re","characterOffsetBegin":9,"characterOffsetEnd":11,"pos":"NNP","before":" ","after":""},{"index":4,"word":":","originalText":":","lemma":":","characterOffsetBegin":11,"characterOffsetEnd":12,"pos":":","before":"","after":" "},{"index":5,"word":"Why","originalText":"Why","lemma":"why","characterOffsetBegin":13,"characterOffsetEnd":16,"pos":"WRB","before":" ","after":" "},{"index":6,"word":"not","originalText":"not","lemma":"not","characterOffsetBegin":17,"characterOffsetEnd":20,"pos":"RB","before":" ","after":" "},{"index":7,"word":"give","originalText":"give","lemma":"give","characterOffsetBegin":21,"characterOffsetEnd":25,"pos":"VB","before":" ","after":" "},{"index":8,"word":"$","originalText":"$","lemma":"$","characterOffsetBegin":26,"characterOffsetEnd":27,"pos":"$","before":" ","after":""},{"index":9,"word":"1","originalText":"1","lemma":"1","characterOffsetBegin":27,"characterOffsetEnd":28,"pos":"CD","before":"","after":" "},{"index":10,"word":"billion","originalText":"billion","lemma":"billion","characterOffsetBegin":29,"characterOffsetEnd":36,"pos":"CD","before":" ","after":" "},{"index":11,"word":"to","originalText":"to","lemma":"to","characterOffsetBegin":37,"characterOffsetEnd":39,"pos":"TO","before":" ","after":" "},{"index":12,"word":"first","originalText":"first","lemma":"first","characterOffsetBegin":40,"characterOffsetEnd":45,"pos":"JJ","before":" ","after":" "},{"index":13,"word":"year-lo","originalText":"year-lo","lemma":"year-lo","characterOffsetBegin":46,"characterOffsetEnd":53,"pos":"JJ","before":" ","after":""}]}]}
{"sentences":[{"index":0,"tokens":[{"index":1,"word":"Organization","originalText":"Organization","lemma":"Organization","characterOffsetBegin":0,"characterOffsetEnd":12,"pos":"NNP","before":"","after":""},{"index":2,"word":":","originalText":":","lemma":":","characterOffsetBegin":12,"characterOffsetEnd":13,"pos":":","before":"","after":" "},{"index":3,"word":"U","originalText":"U","lemma":"U","characterOffsetBegin":14,"characterOffsetEnd":15,"pos":"NNP","before":" ","after":" "},{"index":4,"word":"of","originalText":"of","lemma":"of","characterOffsetBegin":16,"characterOffsetEnd":18,"pos":"IN","before":" ","after":" "},{"index":5,"word":"Toronto","originalText":"Toronto","lemma":"Toronto","characterOffsetBegin":19,"characterOffsetEnd":26,"pos":"NNP","before":" ","after":" "},{"index":6,"word":"Zoology","originalText":"Zoology","lemma":"Zoology","characterOffsetBegin":27,"characterOffsetEnd":34,"pos":"NNP","before":" ","after":""}]}]}
{"sentences":[{"index":0,"tokens":[{"index":1,"word":"Lines","originalText":"Lines","lemma":"Lines","characterOffsetBegin":0,"characterOffsetEnd":5,"pos":"NNPS","before":"","after":""},{"index":2,"word":":","originalText":":","lemma":":","characterOffsetBegin":5,"characterOffsetEnd":6,"pos":":","before":"","after":" "},{"index":3,"word":"16","originalText":"16","lemma":"16","characterOffsetBegin":7,"characterOffsetEnd":9,"pos":"CD","before":" ","after":""}]}]}
{"sentences":[]}
{"sentences":[{"index":0,"tokens":[{"index":1,"word":"In","originalText":"In","lemma":"in","characterOffsetBegin":0,"characterOffsetEnd":2,"pos":"IN","before":"","after":" "},{"index":2,"word":"article","originalText":"article","lemma":"article","characterOffsetBegin":3,"characterOffsetEnd":10,"pos":"NN","before":" ","after":" "},{"index":3,"word":"<C5szvL.I48@oakhill.sps.mot.com>","originalText":"<C5szvL.I48@oakhill.sps.mot.com>","lemma":"<c5szvl.i48@oakhill.sps.mot.com>","characterOffsetBegin":11,"characterOffsetEnd":43,"pos":"NN","before":" ","after":" "},{"index":4,"word":"dong@oakhill.sps.mot.com","originalText":"dong@oakhill.sps.mot.com","lemma":"dong@oakhill.sps.mot.com","characterOffsetBegin":44,"characterOffsetEnd":68,"pos":"NN","before":" ","after":" "},{"index":5,"word":"writes","originalText":"writes","lemma":"write","characterOffsetBegin":69,"characterOffsetEnd":75,"pos":"VBZ","before":" ","after":""},{"index":6,"word":":","originalText":":","lemma":":","characterOffsetBegin":75,"characterOffsetEnd":76,"pos":":","before":"","after":""}]}]}
{"sentences":[{"index":0,"tokens":[{"index":1,"word":">>","originalText":">>","lemma":">>","characterOffsetBegin":0,"characterOffsetEnd":2,"pos":"NN","before":"","after":""},{"index":2,"word":"I","originalText":"I","lemma":"I","characterOffsetBegin":2,"characterOffsetEnd":3,"pos":"PRP","before":"","after":""},{"index":3,"word":"'d","originalText":"'d","lemma":"would","characterOffsetBegin":3,"characterOffsetEnd":5,"pos":"MD","before":"","after":" "},{"index":4,"word":"be","originalText":"be","lemma":"be","characterOffsetBegin":6,"characterOffsetEnd":8,"pos":"VB","before":" ","after":" "},{"index":5,"word":"inclined","originalText":"inclined","lemma":"incline","characterOffsetBegin":9,"characterOffsetEnd":17,"pos":"VBN","before":" ","after":" "},{"index":6,"word":"to","originalText":"to","lemma":"to","characterOffsetBegin":18,"characterOffsetEnd":20,"pos":"TO","before":" ","after":" "},{"index":7,"word":"make","originalText":"make","lemma":"make","characterOffsetBegin":21,"characterOffsetEnd":25,"pos":"VB","before":" ","after":" "},{"index":8,"word":"the","originalText":"the","lemma":"the","characterOffsetBegin":26,"characterOffsetEnd":29,"pos":"DT","before":" ","after":" "},{"index":9,"word":"prize","originalText":"prize","lemma":"prize","characterOffsetBegin":30,"characterOffsetEnd":35,"pos":"NN","before":" ","after":" "},{"index":10,"word":"somewhat","originalText":"somewhat","lemma":"somewhat","characterOffsetBegin":36,"characterOffsetEnd":44,"pos":"RB","before":" ","after":" "},{"index":11,"word":"larger","originalText":"larger","lemma":"larger","characterOffsetBegin":45,"characterOffsetEnd":51,"pos":"JJR","before":" ","after":""},{"index":12,"word":",","originalText":",","lemma":",","characterOffsetBegin":51,"characterOffsetEnd":52,"pos":",","before":"","after":" "},{"index":13,"word":"but","originalText":"but","lemma":"but","characterOffsetBegin":53,"characterOffsetEnd":56,"pos":"CC","before":" ","after":" "},{"index":14,"word":"$","originalText":"$","lemma":"$","characterOffsetBegin":57,"characterOffsetEnd":58,"pos":"$","before":" ","after":""},{"index":15,"word":"1G","originalText":"1G","lemma":"1g","characterOffsetBegin":58,"characterOffsetEnd":60,"pos":"JJ","before":"","after":" "},{"index":16,"word":"might","originalText":"might","lemma":"might","characterOffsetBegin":61,"characterOffsetEnd":66,"pos":"MD","before":" ","after":" "},{"index":17,"word":"be","originalText":"be","lemma":"be","characterOffsetBegin":67,"characterOffsetEnd":69,"pos":"VB","before":" ","after":" "},{"index":18,"word":"enough","originalText":"enough","lemma":"enough","characterOffsetBegin":70,"characterOffsetEnd":76,"pos":"RB","before":" ","after":""},{"index":19,"word":".","originalText":".","lemma":".","characterOffsetBegin":76,"characterOffsetEnd":77,"pos":".","before":"","after":""}]}]}
{"sentences":[{"index":0,"tokens":[{"index":1,"word":">","originalText":">","lemma":">","characterOffsetBegin":0,"characterOffsetEnd":1,"pos":"JJR","before":"","after":""}]}]}
{"sentences":[{"index":0,"tokens":[{"index":1,"word":">","originalText":">","lemma":">","characterOffsetBegin":0,"characterOffsetEnd":1,"pos":"RBR","before":"","after":""},{"index":2,"word":"this","originalText":"this","lemma":"this","characterOffsetBegin":1,"characterOffsetEnd":5,"pos":"DT","before":"","after":" "},{"index":3,"word":"all","originalText":"all","lemma":"all","characterOffsetBegin":6,"characterOffsetEnd":9,"pos":"DT","before":" ","after":" "},{"index":4,"word":"sounds","originalText":"sounds","lemma":"sound","characterOffsetBegin":10,"characterOffsetEnd":16,"pos":"NNS","before":" ","after":" "},{"index":5,"word":"like","originalText":"like","lemma":"like","characterOffsetBegin":17,"characterOffsetEnd":21,"pos":"IN","before":" ","after":" "},{"index":6,"word":"that","originalText":"that","lemma":"that","characterOffsetBegin":22,"characterOffsetEnd":26,"pos":"DT","before":" ","after":" "},{"index":7,"word":"Indecent","originalText":"Indecent","lemma":"Indecent","characterOffsetBegin":27,"characterOffsetEnd":35,"pos":"NNP","before":" ","after":" "},{"index":8,"word":"Proposal","originalText":"Proposal","lemma":"Proposal","characterOffsetBegin":36,"characterOffsetEnd":44,"pos":"NNP","before":" ","after":" "},{"index":9,"word":"movie","originalText":"movie","lemma":"movie","characterOffsetBegin":45,"characterOffsetEnd":50,"pos":"NN","before":" ","after":""},{"index":10,"word":".","originalText":".","lemma":".","characterOffsetBegin":50,"characterOffsetEnd":51,"pos":".","before":"","after":"  "}]},{"index":1,"tokens":[{"index":1,"word":"would","originalText":"would","lemma":"would","characterOffsetBegin":53,"characterOffsetEnd":58,"pos":"MD","before":"  ","after":""},{"index":2,"word":"n't","originalText":"n't","lemma":"not","characterOffsetBegin":58,"characterOffsetEnd":61,"pos":"RB","before":"","after":" "},{"index":3,"word":"there","originalText":"there","lemma":"there","characterOffsetBegin":62,"characterOffsetEnd":67,"pos":"RB","before":" ","after":" "},{"index":4,"word":"be","originalText":"be","lemma":"be","characterOffsetBegin":68,"characterOffsetEnd":70,"pos":"VB","before":" ","after":""}]}]}
{"sentences":[{"index":0,"tokens":[{"index":1,"word":">","originalText":">","lemma":">","characterOffsetBegin":0,"characterOffsetEnd":1,"pos":"JJR","before":"","after":""},{"index":2,"word":"a","originalText":"a","lemma":"a","characterOffsetBegin":1,"characterOffsetEnd":2,"pos":"DT","before":"","after":" "},{"index":3,"word":"lot","originalText":"lot","lemma":"lot","characterOffsetBegin":3,"characterOffsetEnd":6,"pos":"NN","before":" ","after":" "},{"index":4,"word":"of","originalText":"of","lemma":"of","characterOffsetBegin":7,"characterOffsetEnd":9,"pos":"IN","before":" ","after":" "},{"index":5,"word":"people","originalText":"people","lemma":"people","characterOffsetBegin":10,"characterOffsetEnd":16,"pos":"NNS","before":" ","after":" "},{"index":6,"word":"that","originalText":"that","lemma":"that","characterOffsetBegin":17,"characterOffsetEnd":21,"pos":"WDT","before":" ","after":" "},{"index":7,"word":"would","originalText":"would","lemma":"would","characterOffsetBegin":22,"characterOffsetEnd":27,"pos":"MD","before":" ","after":" "},{"index":8,"word":"try","originalText":"try","lemma":"try","characterOffsetBegin":28,"characterOffsetEnd":31,"pos":"VB","before":" ","after":" "},{"index":9,"word":"this","originalText":"this","lemma":"this","characterOffsetBegin":32,"characterOffsetEnd":36,"pos":"DT","before":" ","after":" "},{"index":10,"word":"with","originalText":"with","lemma":"with","characterOffsetBegin":37,"characterOffsetEnd":41,"pos":"IN","before":" ","after":" "},{"index":11,"word":"little","originalText":"little","lemma":"little","characterOffsetBegin":42,"characterOffsetEnd":48,"pos":"JJ","before":" ","after":" "},{"index":12,"word":"hope","originalText":"hope","lemma":"hope","characterOffsetBegin":49,"characterOffsetEnd":53,"pos":"NN","before":" ","after":" "},{"index":13,"word":"of","originalText":"of","lemma":"of","characterOffsetBegin":54,"characterOffsetEnd":56,"pos":"IN","before":" ","after":" "},{"index":14,"word":"working","originalText":"working","lemma":"work","characterOffsetBegin":57,"characterOffsetEnd":64,"pos":"VBG","before":" ","after":" "},{"index":15,"word":"just","originalText":"just","lemma":"just","characterOffsetBegin":65,"characterOffsetEnd":69,"pos":"RB","before":" ","after":""}]}]}
{"sentences":[{"index":0,"tokens":[{"index":1,"word":">","originalText":">","lemma":">","characterOffsetBegin":0,"characterOffsetEnd":1,"pos":"JJR","before":"","after":""},{"index":2,"word":"to","originalText":"to","lemma":"to","characterOffsetBegin":1,"characterOffsetEnd":3,"pos":"TO","before":"","after":" "},{"index":3,"word":"get","originalText":"get","lemma":"get","characterOffsetBegin":4,"characterOffsetEnd":7,"pos":"VB","before":" ","after":" "},{"index":4,"word":"the","originalText":"the","lemma":"the","characterOffsetBegin":8,"characterOffsetEnd":11,"pos":"DT","before":" ","after":" "},{"index":5,"word":"dough","originalText":"dough","lemma":"dough","characterOffsetBegin":12,"characterOffsetEnd":17,"pos":"NN","before":" ","after":""},{"index":6,"word":"?","originalText":"?","lemma":"?","characterOffsetBegin":17,"characterOffsetEnd":18,"pos":".","before":"","after":"  "}]},{"index":1,"tokens":[{"index":1,"word":"if","originalText":"if","lemma":"if","characterOffsetBegin":20,"characterOffsetEnd":22,"pos":"IN","before":"  ","after":" "},{"index":2,"word":"you","originalText":"you","lemma":"you","characterOffsetBegin":23,"characterOffsetEnd":26,"pos":"PRP","before":" ","after":" "},{"index":3,"word":"have","originalText":"have","lemma":"have","characterOffsetBegin":27,"characterOffsetEnd":31,"pos":"VBP","before":" ","after":" "},{"index":4,"word":"a","originalText":"a","lemma":"a","characterOffsetBegin":32,"characterOffsetEnd":33,"pos":"DT","before":" ","after":" "},{"index":5,"word":"1:100","originalText":"1:100","lemma":"1:100","characterOffsetBegin":34,"characterOffsetEnd":39,"pos":"CD","before":" ","after":" "},{"index":6,"word":"chance","originalText":"chance","lemma":"chance","characterOffsetBegin":40,"characterOffsetEnd":46,"pos":"NN","before":" ","after":" "},{"index":7,"word":"and","originalText":"and","lemma":"and","characterOffsetBegin":47,"characterOffsetEnd":50,"pos":"CC","before":" ","after":" "},{"index":8,"word":"it","originalText":"it","lemma":"it","characterOffsetBegin":51,"characterOffsetEnd":53,"pos":"PRP","before":" ","after":" "},{"index":9,"word":"costs","originalText":"costs","lemma":"cost","characterOffsetBegin":54,"characterOffsetEnd":59,"pos":"VBZ","before":" ","after":" "},{"index":10,"word":"you","originalText":"you","lemma":"you","characterOffsetBegin":60,"characterOffsetEnd":63,"pos":"PRP","before":" ","after":" "},{"index":11,"word":"$","originalText":"$","lemma":"$","characterOffsetBegin":64,"characterOffsetEnd":65,"pos":"$","before":" ","after":""},{"index":12,"word":"10Mil","originalText":"10Mil","lemma":"10mil","characterOffsetBegin":65,"characterOffsetEnd":70,"pos":"JJ","before":"","after":""},{"index":13,"word":",","originalText":",","lemma":",","characterOffsetBegin":70,"characterOffsetEnd":71,"pos":",","before":"","after":""}]}]}
{"sentences":[{"index":0,"tokens":[{"index":1,"word":">","originalText":">","lemma":">","characterOffsetBegin":0,"characterOffsetEnd":1,"pos":"JJR","before":"","after":""},{"index":2,"word":"then","originalText":"then","lemma":"then","characterOffsetBegin":1,"characterOffsetEnd":5,"pos":"RB","before":"","after":" "},{"index":3,"word":"you","originalText":"you","lemma":"you","characterOffsetBegin":6,"characterOffsetEnd":9,"pos":"PRP","before":" ","after":" "},{"index":4,"word":"might","originalText":"might","lemma":"might","characterOffsetBegin":10,"characterOffsetEnd":15,"pos":"MD","before":" ","after":" "},{"index":5,"word":"pay","originalText":"pay","lemma":"pay","characterOffsetBegin":16,"characterOffsetEnd":19,"pos":"VB","before":" ","after":" "},{"index":6,"word":"some","originalText":"some","lemma":"some","characterOffsetBegin":20,"characterOffsetEnd":24,"pos":"DT","before":" ","after":" "},{"index":7,"word":"stooge","originalText":"stooge","lemma":"stooge","characterOffsetBegin":25,"characterOffsetEnd":31,"pos":"NN","before":" ","after":" "},{"index":8,"word":"a","originalText":"a","lemma":"a","characterOffsetBegin":32,"characterOffsetEnd":33,"pos":"DT","before":" ","after":" "},{"index":9,"word":"few","originalText":"few","lemma":"few","characterOffsetBegin":34,"characterOffsetEnd":37,"pos":"JJ","before":" ","after":" "},{"index":10,"word":"grand","originalText":"grand","lemma":"grand","characterOffsetBegin":38,"characterOffsetEnd":43,"pos":"JJ","before":" ","after":" "},{"index":11,"word":"to","originalText":"to","lemma":"to","characterOffsetBegin":44,"characterOffsetEnd":46,"pos":"TO","before":" ","after":" "},{"index":12,"word":"be","originalText":"be","lemma":"be","characterOffsetBegin":47,"characterOffsetEnd":49,"pos":"VB","before":" ","after":" "},{"index":13,"word":"your","originalText":"your","lemma":"you","characterOffsetBegin":50,"characterOffsetEnd":54,"pos":"PRP$","before":" ","after":" "},{"index":14,"word":"lucky","originalText":"lucky","lemma":"lucky","characterOffsetBegin":55,"characterOffsetEnd":60,"pos":"JJ","before":" ","after":" "},{"index":15,"word":"hero","originalText":"hero","lemma":"hero","characterOffsetBegin":61,"characterOffsetEnd":65,"pos":"NN","before":" ","after":""},{"index":16,"word":".","originalText":".","lemma":".","characterOffsetBegin":65,"characterOffsetEnd":66,"pos":".","before":"","after":""}]}]}
{"sentences":[{"index":0,"tokens":[{"index":1,"word":">","originalText":">","lemma":">","characterOffsetBegin":0,"characterOffsetEnd":1,"pos":"JJR","before":"","after":""},{"index":2,"word":"just","originalText":"just","lemma":"just","characterOffsetBegin":1,"characterOffsetEnd":5,"pos":"RB","before":"","after":" "},{"index":3,"word":"send","originalText":"send","lemma":"send","characterOffsetBegin":6,"characterOffsetEnd":10,"pos":"VB","before":" ","after":" "},{"index":4,"word":"up","originalText":"up","lemma":"up","characterOffsetBegin":11,"characterOffsetEnd":13,"pos":"RP","before":" ","after":" "},{"index":5,"word":"a","originalText":"a","lemma":"a","characterOffsetBegin":14,"characterOffsetEnd":15,"pos":"DT","before":" ","after":" "},{"index":6,"word":"few","originalText":"few","lemma":"few","characterOffsetBegin":16,"characterOffsetEnd":19,"pos":"JJ","before":" ","after":" "},{"index":7,"word":"dozen","originalText":"dozen","lemma":"dozen","characterOffsetBegin":20,"characterOffsetEnd":25,"pos":"NN","before":" ","after":" "},{"index":8,"word":"and","originalText":"and","lemma":"and","characterOffsetBegin":26,"characterOffsetEnd":29,"pos":"CC","before":" ","after":" "},{"index":9,"word":"1","originalText":"1","lemma":"1","characterOffsetBegin":30,"characterOffsetEnd":31,"pos":"CD","before":" ","after":" "},{"index":10,"word":"is","originalText":"is","lemma":"be","characterOffsetBegin":32,"characterOffsetEnd":34,"pos":"VBZ","before":" ","after":" "},{"index":11,"word":"bound","originalText":"bound","lemma":"bind","characterOffsetBegin":35,"characterOffsetEnd":40,"pos":"VBN","before":" ","after":" "},{"index":12,"word":"to","originalText":"to","lemma":"to","characterOffsetBegin":41,"characterOffsetEnd":43,"pos":"TO","before":" ","after":" "},{"index":13,"word":"survive","originalText":"survive","lemma":"survive","characterOffsetBegin":44,"characterOffsetEnd":51,"pos":"VB","before":" ","after":" "},{"index":14,"word":"enough","originalText":"enough","lemma":"enough","characterOffsetBegin":52,"characterOffsetEnd":58,"pos":"RB","before":" ","after":" "},{"index":15,"word":"to","originalText":"to","lemma":"to","characterOffsetBegin":59,"characterOffsetEnd":61,"pos":"TO","before":" ","after":" "},{"index":16,"word":"make","originalText":"make","lemma":"make","characterOffsetBegin":62,"characterOffsetEnd":66,"pos":"VB","before":" ","after":" "},{"index":17,"word":"YOU","originalText":"YOU","lemma":"you","characterOffsetBegin":67,"characterOffsetEnd":70,"pos":"PRP","before":" ","after":""}]}]}
{"sentences":[{"index":0,"tokens":[{"index":1,"word":">","originalText":">","lemma":">","characterOffsetBegin":0,"characterOffsetEnd":1,"pos":"JJR","before":"","after":""},{"index":2,"word":"rich","originalText":"rich","lemma":"rich","characterOffsetBegin":1,"characterOffsetEnd":5,"pos":"JJ","before":"","after":""},{"index":3,"word":".","originalText":".","lemma":".","characterOffsetBegin":5,"characterOffsetEnd":6,"pos":".","before":"","after":""}]}]}
{"sentences":[]}
{"sentences":[{"index":0,"tokens":[{"index":1,"word":"Any","originalText":"Any","lemma":"any","characterOffsetBegin":0,"characterOffsetEnd":3,"pos":"DT","before":"","after":" "},{"index":2,"word":"prize","originalText":"prize","lemma":"prize","characterOffsetBegin":4,"characterOffsetEnd":9,"pos":"NN","before":" ","after":" "},{"index":3,"word":"like","originalText":"like","lemma":"like","characterOffsetBegin":10,"characterOffsetEnd":14,"pos":"IN","before":" ","after":" "},{"index":4,"word":"this","originalText":"this","lemma":"this","characterOffsetBegin":15,"characterOffsetEnd":19,"pos":"DT","before":" ","after":" "},{"index":5,"word":"is","originalText":"is","lemma":"be","characterOffsetBegin":20,"characterOffsetEnd":22,"pos":"VBZ","before":" ","after":" "},{"index":6,"word":"going","originalText":"going","lemma":"go","characterOffsetBegin":23,"characterOffsetEnd":28,"pos":"VBG","before":" ","after":" "},{"index":7,"word":"to","originalText":"to","lemma":"to","characterOffsetBegin":29,"characterOffsetEnd":31,"pos":"TO","before":" ","after":" "},{"index":8,"word":"need","originalText":"need","lemma":"need","characterOffsetBegin":32,"characterOffsetEnd":36,"pos":"VB","before":" ","after":" "},{"index":9,"word":"to","originalText":"to","lemma":"to","characterOffsetBegin":37,"characterOffsetEnd":39,"pos":"TO","before":" ","after":" "},{"index":10,"word":"be","originalText":"be","lemma":"be","characterOffsetBegin":40,"characterOffsetEnd":42,"pos":"VB","before":" ","after":" "},{"index":11,"word":"worded","originalText":"worded","lemma":"word","characterOffsetBegin":43,"characterOffsetEnd":49,"pos":"VBN","before":" ","after":" "},{"index":12,"word":"carefully","originalText":"carefully","lemma":"carefully","characterOffsetBegin":50,"characterOffsetEnd":59,"pos":"RB","before":" ","after":" "},{"index":13,"word":"enough","originalText":"enough","lemma":"enough","characterOffsetBegin":60,"characterOffsetEnd":66,"pos":"RB","before":" ","after":" "},{"index":14,"word":"that","originalText":"that","lemma":"that","characterOffsetBegin":67,"characterOffsetEnd":71,"pos":"IN","before":" ","after":""}]}]}
{"sentences":[{"index":0,"tokens":[{"index":1,"word":"you","originalText":"you","lemma":"you","characterOffsetBegin":0,"characterOffsetEnd":3,"pos":"PRP","before":"","after":" "},{"index":2,"word":"can","originalText":"can","lemma":"can","characterOffsetBegin":4,"characterOffsetEnd":7,"pos":"MD","before":" ","after":""},{"index":3,"word":"not","originalText":"not","lemma":"not","characterOffsetBegin":7,"characterOffsetEnd":10,"pos":"RB","before":"","after":" "},{"index":4,"word":"get","originalText":"get","lemma":"get","characterOffsetBegin":11,"characterOffsetEnd":14,"pos":"VB","before":" ","after":" "},{"index":5,"word":"it","originalText":"it","lemma":"it","characterOffsetBegin":15,"characterOffsetEnd":17,"pos":"PRP","before":" ","after":" "},{"index":6,"word":"without","originalText":"without","lemma":"without","characterOffsetBegin":18,"characterOffsetEnd":25,"pos":"IN","before":" ","after":" "},{"index":7,"word":"demonstrating","originalText":"demonstrating","lemma":"demonstrate","characterOffsetBegin":26,"characterOffsetEnd":39,"pos":"VBG","before":" ","after":" "},{"index":8,"word":"sustained","originalText":"sustained","lemma":"sustained","characterOffsetBegin":40,"characterOffsetEnd":49,"pos":"JJ","before":" ","after":" "},{"index":9,"word":"and","originalText":"and","lemma":"and","characterOffsetBegin":50,"characterOffsetEnd":53,"pos":"CC","before":" ","after":" "},{"index":10,"word":"reliable","originalText":"reliable","lemma":"reliable","characterOffsetBegin":54,"characterOffsetEnd":62,"pos":"JJ","before":" ","after":" "},{"index":11,"word":"capability","originalText":"capability","lemma":"capability","characterOffsetBegin":63,"characterOffsetEnd":73,"pos":"NN","before":" ","after":""},{"index":12,"word":",","originalText":",","lemma":",","characterOffsetBegin":73,"characterOffsetEnd":74,"pos":",","before":"","after":""}]}]}
{"sentences":[{"index":0,"tokens":[{"index":1,"word":"rather","originalText":"rather","lemma":"rather","characterOffsetBegin":0,"characterOffsetEnd":6,"pos":"RB","before":"","after":" "},{"index":2,"word":"than","originalText":"than","lemma":"than","characterOffsetBegin":7,"characterOffsetEnd":11,"pos":"IN","before":" ","after":" "},{"index":3,"word":"a","originalText":"a","lemma":"a","characterOffsetBegin":12,"characterOffsetEnd":13,"pos":"DT","before":" ","after":" "},{"index":4,"word":"lucky","originalText":"lucky","lemma":"lucky","characterOffsetBegin":14,"characterOffsetEnd":19,"pos":"JJ","before":" ","after":" "},{"index":5,"word":"one-shot","originalText":"one-shot","lemma":"one-shot","characterOffsetBegin":20,"characterOffsetEnd":28,"pos":"JJ","before":" ","after":""},{"index":6,"word":".","originalText":".","lemma":".","characterOffsetBegin":28,"characterOffsetEnd":29,"pos":".","before":"","after":"  "}]},{"index":1,"tokens":[{"index":1,"word":"It","originalText":"It","lemma":"it","characterOffsetBegin":31,"characterOffsetEnd":33,"pos":"PRP","before":"  ","after":" "},{"index":2,"word":"can","originalText":"can","lemma":"can","characterOffsetBegin":34,"characterOffsetEnd":37,"pos":"MD","before":" ","after":" "},{"index":3,"word":"be","originalText":"be","lemma":"be","characterOffsetBegin":38,"characterOffsetEnd":40,"pos":"VB","before":" ","after":" "},{"index":4,"word":"done","originalText":"done","lemma":"do","characterOffsetBegin":41,"characterOffsetEnd":45,"pos":"VBN","before":" ","after":""},{"index":5,"word":".","originalText":".","lemma":".","characterOffsetBegin":45,"characterOffsetEnd":46,"pos":".","before":"","after":""}]}]}
{"sentences":[{"index":0,"tokens":[{"index":1,"word":"--","originalText":"--","lemma":"--","characterOffsetBegin":0,"characterOffsetEnd":2,"pos":":","before":"","after":""}]}]}
{"sentences":[{"index":0,"tokens":[{"index":1,"word":"All","originalText":"All","lemma":"all","characterOffsetBegin":0,"characterOffsetEnd":3,"pos":"DT","before":"","after":" "},{"index":2,"word":"work","originalText":"work","lemma":"work","characterOffsetBegin":4,"characterOffsetEnd":8,"pos":"NN","before":" ","after":" "},{"index":3,"word":"is","originalText":"is","lemma":"be","characterOffsetBegin":9,"characterOffsetEnd":11,"pos":"VBZ","before":" ","after":" "},{"index":4,"word":"one","originalText":"one","lemma":"one","characterOffsetBegin":12,"characterOffsetEnd":15,"pos":"CD","before":" ","after":" "},{"index":5,"word":"man","originalText":"man","lemma":"man","characterOffsetBegin":16,"characterOffsetEnd":19,"pos":"NN","before":" ","after":""},{"index":6,"word":"'s","originalText":"'s","lemma":"'s","characterOffsetBegin":19,"characterOffsetEnd":21,"pos":"POS","before":"","after":" "},{"index":7,"word":"work","originalText":"work","lemma":"work","characterOffsetBegin":22,"characterOffsetEnd":26,"pos":"NN","before":" ","after":""},{"index":8,"word":".","originalText":".","lemma":".","characterOffsetBegin":26,"characterOffsetEnd":27,"pos":".","before":"","after":"             "}]},{"index":1,"tokens":[{"index":1,"word":"|","originalText":"|","lemma":"|","characterOffsetBegin":40,"characterOffsetEnd":41,"pos":"NN","before":"             ","after":" "},{"index":2,"word":"Henry","originalText":"Henry","lemma":"Henry","characterOffsetBegin":42,"characterOffsetEnd":47,"pos":"NNP","before":" ","after":" "},{"index":3,"word":"Spencer","originalText":"Spencer","lemma":"Spencer","characterOffsetBegin":48,"characterOffsetEnd":55,"pos":"NNP","before":" ","after":" "},{"index":4,"word":"@","originalText":"@","lemma":"@","characterOffsetBegin":56,"characterOffsetEnd":57,"pos":"IN","before":" ","after":" "},{"index":5,"word":"U","originalText":"U","lemma":"U","characterOffsetBegin":58,"characterOffsetEnd":59,"pos":"NNP","before":" ","after":" "},{"index":6,"word":"of","originalText":"of","lemma":"of","characterOffsetBegin":60,"characterOffsetEnd":62,"pos":"IN","before":" ","after":" "},{"index":7,"word":"Toronto","originalText":"Toronto","lemma":"Toronto","characterOffsetBegin":63,"characterOffsetEnd":70,"pos":"NNP","before":" ","after":" "},{"index":8,"word":"Zoology","originalText":"Zoology","lemma":"Zoology","characterOffsetBegin":71,"characterOffsetEnd":78,"pos":"NNP","before":" ","after":""}]}]}
{"sentences":[{"index":0,"tokens":[{"index":1,"word":"-","originalText":"-","lemma":"-","characterOffsetBegin":0,"characterOffsetEnd":1,"pos":":","before":"","after":" "},{"index":2,"word":"Kipling","originalText":"Kipling","lemma":"kiple","characterOffsetBegin":2,"characterOffsetEnd":9,"pos":"VBG","before":" ","after":"           "},{"index":3,"word":"|","originalText":"|","lemma":"|","characterOffsetBegin":20,"characterOffsetEnd":21,"pos":"CD","before":"           ","after":"  "},{"index":4,"word":"henry@zoo.toronto.edu","originalText":"henry@zoo.toronto.edu","lemma":"henry@zoo.toronto.edu","characterOffsetBegin":23,"characterOffsetEnd":44,"pos":"NN","before":"  ","after":"  "},{"index":5,"word":"utzoo!henry","originalText":"utzoo!henry","lemma":"utzoo!henry","characterOffsetBegin":46,"characterOffsetEnd":57,"pos":"NN","before":"  ","after":""}]}]}
