{"sentences":[{"index":0,"tokens":[{"index":1,"word":"From","originalText":"From","lemma":"from","characterOffsetBegin":0,"characterOffsetEnd":4,"pos":"IN","before":"","after":""},{"index":2,"word":":","originalText":":","lemma":":","characterOffsetBegin":4,"characterOffsetEnd":5,"pos":":","before":"","after":" "},{"index":3,"word":"abdkw@stdvax","originalText":"abdkw@stdvax","lemma":"abdkw@stdvax","characterOffsetBegin":6,"characterOffsetEnd":18,"pos":"NN","before":" ","after":" "},{"index":4,"word":"-LRB-","originalText":"(","lemma":"-lrb-","characterOffsetBegin":19,"characterOffsetEnd":20,"pos":"-LRB-","before":" ","after":""},{"index":5,"word":"David","originalText":"David","lemma":"David","characterOffsetBegin":20,"characterOffsetEnd":25,"pos":"NNP","before":"","after":" "},{"index":6,"word":"Ward","originalText":"Ward","lemma":"Ward","characterOffsetBegin":26,"characterOffsetEnd":30,"pos":"NNP","before":" ","after":""},{"index":7,"word":"-RRB-","originalText":")","lemma":"-rrb-","characterOffsetBegin":30,"characterOffsetEnd":31,"pos":"-RRB-","before":"","after":""}]}]}
{"sentences":[{"index":0,"tokens":[{"index":1,"word":"Subject","originalText":"Subject","lemma":"Subject","characterOffsetBegin":0,"characterOffsetEnd":7,"pos":"NNP","before":"","after":""},{"index":2,"word":":","originalText":":","lemma":":","characterOffsetBegin":7,"characterOffsetEnd":8,"pos":":","before":"","after":" "},{"index":3,"word":"Re","originalText":"Re","lemma":"Re","characterOffsetBegin":9,"characterOffsetEnd":11,"pos":"NNP","before":" ","after":""},{"index":4,"word":":","originalText":":","lemma":":","characterOffsetBegin":11,"characterOffsetEnd":12,"pos":":","before":"","after":" "},{"index":5,"word":"Keeping","originalText":"Keeping","lemma":"keep","characterOffsetBegin":13,"characterOffsetEnd":20,"pos":"VBG","before":" ","after":" "},{"index":6,"word":"Spacecraft","originalText":"Spacecraft","lemma":"spacecraft","characterOffsetBegin":21,"characterOffsetEnd":31,"pos":"NN","before":" ","after":" "},{"index":7,"word":"on","originalText":"on","lemma":"on","characterOffsetBegin":32,"characterOffsetEnd":34,"pos":"IN","before":" ","after":" "},{"index":8,"word":"after","originalText":"after","lemma":"after","characterOffsetBegin":35,"characterOffsetEnd":40,"pos":"IN","before":" ","after":" "},{"index":9,"word":"Funding","originalText":"Funding","lemma":"Funding","characterOffsetBegin":41,"characterOffsetEnd":48,"pos":"NNP","before":" ","after":" "},{"index":10,"word":"Cuts","originalText":"Cuts","lemma":"cut","characterOffsetBegin":49,"characterOffsetEnd":53,"pos":"NNS","before":" ","after":""},{"index":11,"word":".","originalText":".","lemma":".","characterOffsetBegin":53,"characterOffsetEnd":54,"pos":".","before":"","after":""}]}]}
{"sentences":[{"index":0,"tokens":[{"index":1,"word":"News-Software","originalText":"News-Software","lemma":"News-Software","characterOffsetBegin":0,"characterOffsetEnd":13,"pos":"NNP","before":"","after":""},{"index":2,"word":":","originalText":":","lemma":":","characterOffsetBegin":13,"characterOffsetEnd":14,"pos":":","before":"","after":" "},{"index":3,"word":"VAX/VMS","originalText":"VAX/VMS","lemma":"vax/vms","characterOffsetBegin":15,"characterOffsetEnd":22,"pos":"NN","before":" ","after":" "},{"index":4,"word":"VNEWS","originalText":"VNEWS","lemma":"vnews","characterOffsetBegin":23,"characterOffsetEnd":28,"pos":"NN","before":" ","after":" "},{"index":5,"word":"1.4-b1","originalText":"1.4-b1","lemma":"1.4-b1","characterOffsetBegin":29,"characterOffsetEnd":35,"pos":"NN","before":" ","after":""}]}]}
{"sentences":[{"index":0,"tokens":[{"index":1,"word":"Organization","originalText":"Organization","lemma":"Organization","characterOffsetBegin":0,"characterOffsetEnd":12,"pos":"NNP","before":"","after":""},{"index":2,"word":":","originalText":":","lemma":":","characterOffsetBegin":12,"characterOffsetEnd":13,"pos":":","before":"","after":" "},{"index":3,"word":"Goddard","originalText":"Goddard","lemma":"Goddard","characterOffsetBegin":14,"characterOffsetEnd":21,"pos":"NNP","before":" ","after":" "},{"index":4,"word":"Space","originalText":"Space","lemma":"Space","characterOffsetBegin":22,"characterOffsetEnd":27,"pos":"NNP","before":" ","after":" "},{"index":5,"word":"Flight","originalText":"Flight","lemma":"Flight","characterOffsetBegin":28,"characterOffsetEnd":34,"pos":"NNP","before":" ","after":" "},{"index":6,"word":"Center","originalText":"Center","lemma":"Center","characterOffsetBegin":35,"characterOffsetEnd":41,"pos":"NNP","before":" ","after":" "},{"index":7,"word":"-","originalText":"-","lemma":"-","characterOffsetBegin":42,"characterOffsetEnd":43,"pos":":","before":" ","after":" "},{"index":8,"word":"Robotics","originalText":"Robotics","lemma":"Robotics","characterOffsetBegin":44,"characterOffsetEnd":52,"pos":"NNP","before":" ","after":" "},{"index":9,"word":"Lab","originalText":"Lab","lemma":"Lab","characterOffsetBegin":53,"characterOffsetEnd":56,"pos":"NNP","before":" ","after":""}]}]}
{"sentences":[{"index":0,"tokens":[{"index":1,"word":"Lines","originalText":"Lines","lemma":"Lines","characterOffsetBegin":0,"characterOffsetEnd":5,"pos":"NNPS","before":"","after":""},{"index":2,"word":":","originalText":":","lemma":":","characterOffsetBegin":5,"characterOffsetEnd":6,"pos":":","before":"","after":" "},{"index":3,"word":"34","originalText":"34","lemma":"34","characterOffsetBegin":7,"characterOffsetEnd":9,"pos":"CD","before":" ","after":""}]}]}
{"sentences":[]}
{"sentences":[{"index":0,"tokens":[{"index":1,"word":"In","originalText":"In","lemma":"in","characterOffsetBegin":0,"characterOffsetEnd":2,"pos":"IN","before":"","after":" "},{"index":2,"word":"article","originalText":"article","lemma":"article","characterOffsetBegin":3,"characterOffsetEnd":10,"pos":"NN","before":" ","after":" "},{"index":3,"word":"<20APR199321040621@kelvin.jpl.nasa.gov>","originalText":"<20APR199321040621@kelvin.jpl.nasa.gov>","lemma":"<20apr199321040621@kelvin.jpl.nasa.gov>","characterOffsetBegin":11,"characterOffsetEnd":50,"pos":"NN","before":" ","after":""},{"index":4,"word":",","originalText":",","lemma":",","characterOffsetBegin":50,"characterOffsetEnd":51,"pos":",","before":"","after":" "},{"index":5,"word":"baalke@kelvin.jpl.nasa.gov","originalText":"baalke@kelvin.jpl.nasa.gov","lemma":"baalke@kelvin.jpl.nasa.gov","characterOffsetBegin":52,"characterOffsetEnd":78,"pos":"NN","before":" ","after":" "},{"index":6,"word":"-LRB-","originalText":"(","lemma":"-lrb-","characterOffsetBegin":79,"characterOffsetEnd":80,"pos":"-LRB-","before":" ","after":""},{"index":7,"word":"Ron","originalText":"Ron","lemma":"Ron","characterOffsetBegin":80,"characterOffsetEnd":83,"pos":"NNP","before":"","after":" "},{"index":8,"word":"Baalke","originalText":"Baalke","lemma":"Baalke","characterOffsetBegin":84,"characterOffsetEnd":90,"pos":"NNP","before":" ","after":""},{"index":9,"word":"-RRB-","originalText":")","lemma":"-rrb-","characterOffsetBegin":90,"characterOffsetEnd":91,"pos":"-RRB-","before":"","after":" "},{"index":10,"word":"writes","originalText":"writes","lemma":"write","characterOffsetBegin":92,"characterOffsetEnd":98,"pos":"VBZ","before":" ","after":""},{"index":11,"word":"...","originalText":"...","lemma":"...","characterOffsetBegin":98,"characterOffsetEnd":101,"pos":":","before":"","after":""}]}]}
{"sentences":[{"index":0,"tokens":[{"index":1,"word":">","originalText":">","lemma":">","characterOffsetBegin":0,"characterOffsetEnd":1,"pos":"JJR","before":"","after":""},{"index":2,"word":"In","originalText":"In","lemma":"in","characterOffsetBegin":1,"characterOffsetEnd":3,"pos":"IN","before":"","after":" "},{"index":3,"word":"article","originalText":"article","lemma":"article","characterOffsetBegin":4,"characterOffsetEnd":11,"pos":"NN","before":" ","after":" "},{"index":4,"word":"<1993Apr20.204335.157595@zeus.calpoly.edu>","originalText":"<1993Apr20.204335.157595@zeus.calpoly.edu>","lemma":"<1993apr20.204335.157595@zeus.calpoly.edu>","characterOffsetBegin":12,"characterOffsetEnd":54,"pos":"NN","before":" ","after":""},{"index":5,"word":",","originalText":",","lemma":",","characterOffsetBegin":54,"characterOffsetEnd":55,"pos":",","before":"","after":" "},{"index":6,"word":"jgreen@trumpet.calpoly.edu","originalText":"jgreen@trumpet.calpoly.edu","lemma":"jgreen@trumpet.calpoly.edu","characterOffsetBegin":56,"characterOffsetEnd":82,"pos":"NN","before":" ","after":" "},{"index":7,"word":"-LRB-","originalText":"(","lemma":"-lrb-","characterOffsetBegin":83,"characterOffsetEnd":84,"pos":"-LRB-","before":" ","after":""},{"index":8,"word":"James","originalText":"James","lemma":"James","characterOffsetBegin":84,"characterOffsetEnd":89,"pos":"NNP","before":"","after":" "},{"index":9,"word":"Thomas","originalText":"Thomas","lemma":"Thomas","characterOffsetBegin":90,"characterOffsetEnd":96,"pos":"NNP","before":" ","after":" "},{"index":10,"word":"Green","originalText":"Green","lemma":"Green","characterOffsetBegin":97,"characterOffsetEnd":102,"pos":"NNP","before":" ","after":""},{"index":11,"word":"-RRB-","originalText":")","lemma":"-rrb-","characterOffsetBegin":102,"characterOffsetEnd":103,"pos":"-RRB-","before":"","after":" "},{"index":12,"word":"writes","originalText":"writes","lemma":"write","characterOffsetBegin":104,"characterOffsetEnd":110,"pos":"VBZ","before":" ","after":""},{"index":13,"word":"...","originalText":"...","lemma":"...","characterOffsetBegin":110,"characterOffsetEnd":113,"pos":":","before":"","after":""}]}]}
{"sentences":[{"index":0,"tokens":[{"index":1,"word":">>","originalText":">>","lemma":">>","characterOffsetBegin":0,"characterOffsetEnd":2,"pos":"NN","before":"","after":""},{"index":2,"word":"Why","originalText":"Why","lemma":"why","characterOffsetBegin":2,"characterOffsetEnd":5,"pos":"WRB","before":"","after":" "},{"index":3,"word":"do","originalText":"do","lemma":"do","characterOffsetBegin":6,"characterOffsetEnd":8,"pos":"VBP","before":" ","after":" "},{"index":4,"word":"spacecraft","originalText":"spacecraft","lemma":"spacecraft","characterOffsetBegin":9,"characterOffsetEnd":19,"pos":"NN","before":" ","after":" "},{"index":5,"word":"have","originalText":"have","lemma":"have","characterOffsetBegin":20,"characterOffsetEnd":24,"pos":"VBP","before":" ","after":" "},{"index":6,"word":"to","originalText":"to","lemma":"to","characterOffsetBegin":25,"characterOffsetEnd":27,"pos":"TO","before":" ","after":" "},{"index":7,"word":"be","originalText":"be","lemma":"be","characterOffsetBegin":28,"characterOffsetEnd":30,"pos":"VB","before":" ","after":" "},{"index":8,"word":"shut","originalText":"shut","lemma":"shut","characterOffsetBegin":31,"characterOffsetEnd":35,"pos":"VBN","before":" ","after":" "},{"index":9,"word":"off","originalText":"off","lemma":"off","characterOffsetBegin":36,"characterOffsetEnd":39,"pos":"RP","before":" ","after":" "},{"index":10,"word":"after","originalText":"after","lemma":"after","characterOffsetBegin":40,"characterOffsetEnd":45,"pos":"IN","before":" ","after":" "},{"index":11,"word":"funding","originalText":"funding","lemma":"fund","characterOffsetBegin":46,"characterOffsetEnd":53,"pos":"VBG","before":" ","after":" "},{"index":12,"word":"cuts","originalText":"cuts","lemma":"cut","characterOffsetBegin":54,"characterOffsetEnd":58,"pos":"NNS","before":" ","after":""},{"index":13,"word":".","originalText":".","lemma":".","characterOffsetBegin":58,"characterOffsetEnd":59,"pos":".","before":"","after":"  "}]},{"index":1,"tokens":[{"index":1,"word":"For","originalText":"For","lemma":"for","characterOffsetBegin":61,"characterOffsetEnd":64,"pos":"IN","before":"  ","after":""}]}]}
{"sentences":[{"index":0,"tokens":[{"index":1,"word":">>","originalText":">>","lemma":">>","characterOffsetBegin":0,"characterOffsetEnd":2,"pos":"NN","before":"","after":""},{"index":2,"word":"example","originalText":"example","lemma":"example","characterOffsetBegin":2,"characterOffsetEnd":9,"pos":"NN","before":"","after":""},{"index":3,"word":",","originalText":",","lemma":",","characterOffsetBegin":9,"characterOffsetEnd":10,"pos":",","before":"","after":" "},{"index":4,"word":"Why","originalText":"Why","lemma":"why","characterOffsetBegin":11,"characterOffsetEnd":14,"pos":"WRB","before":" ","after":" "},{"index":5,"word":"could","originalText":"could","lemma":"could","characterOffsetBegin":15,"characterOffsetEnd":20,"pos":"MD","before":" ","after":""},{"index":6,"word":"n't","originalText":"n't","lemma":"not","characterOffsetBegin":20,"characterOffsetEnd":23,"pos":"RB","before":"","after":" "},{"index":7,"word":"Magellan","originalText":"Magellan","lemma":"Magellan","characterOffsetBegin":24,"characterOffsetEnd":32,"pos":"NNP","before":" ","after":" "},{"index":8,"word":"just","originalText":"just","lemma":"just","characterOffsetBegin":33,"characterOffsetEnd":37,"pos":"RB","before":" ","after":" "},{"index":9,"word":"be","originalText":"be","lemma":"be","characterOffsetBegin":38,"characterOffsetEnd":40,"pos":"VB","before":" ","after":" "},{"index":10,"word":"told","originalText":"told","lemma":"tell","characterOffsetBegin":41,"characterOffsetEnd":45,"pos":"VBN","before":" ","after":" "},{"index":11,"word":"to","originalText":"to","lemma":"to","characterOffsetBegin":46,"characterOffsetEnd":48,"pos":"TO","before":" ","after":" "},{"index":12,"word":"go","originalText":"go","lemma":"go","characterOffsetBegin":49,"characterOffsetEnd":51,"pos":"VB","before":" ","after":" "},{"index":13,"word":"into","originalText":"into","lemma":"into","characterOffsetBegin":52,"characterOffsetEnd":56,"pos":"IN","before":" ","after":" "},{"index":14,"word":"a","originalText":"a","lemma":"a","characterOffsetBegin":57,"characterOffsetEnd":58,"pos":"DT","before":" ","after":" "},{"index":15,"word":"``","originalText":"\"","lemma":"``","characterOffsetBegin":59,"characterOffsetEnd":60,"pos":"``","before":" ","after":""},{"index":16,"word":"safe","originalText":"safe","lemma":"safe","characterOffsetBegin":60,"characterOffsetEnd":64,"pos":"JJ","before":"","after":""},{"index":17,"word":"''","originalText":"\"","lemma":"''","characterOffsetBegin":64,"characterOffsetEnd":65,"pos":"''","before":"","after":""}]}]}
{"sentences":[{"index":0,"tokens":[{"index":1,"word":">>","originalText":">>","lemma":">>","characterOffsetBegin":0,"characterOffsetEnd":2,"pos":"NN","before":"","after":""},{"index":2,"word":"mode","originalText":"mode","lemma":"mode","characterOffsetBegin":2,"characterOffsetEnd":6,"pos":"NN","before":"","after":" "},{"index":3,"word":"and","originalText":"and","lemma":"and","characterOffsetBegin":7,"characterOffsetEnd":10,"pos":"CC","before":" ","after":" "},{"index":4,"word":"stay","originalText":"stay","lemma":"stay","characterOffsetBegin":11,"characterOffsetEnd":15,"pos":"VB","before":" ","after":" "},{"index":5,"word":"bobbing","originalText":"bobbing","lemma":"bob","characterOffsetBegin":16,"characterOffsetEnd":23,"pos":"VBG","before":" ","after":" "},{"index":6,"word":"about","originalText":"about","lemma":"about","characterOffsetBegin":24,"characterOffsetEnd":29,"pos":"IN","before":" ","after":" "},{"index":7,"word":"Venus","originalText":"Venus","lemma":"Venus","characterOffsetBegin":30,"characterOffsetEnd":35,"pos":"NNP","before":" ","after":" "},{"index":8,"word":"in","originalText":"in","lemma":"in","characterOffsetBegin":36,"characterOffsetEnd":38,"pos":"IN","before":" ","after":" "},{"index":9,"word":"a","originalText":"a","lemma":"a","characterOffsetBegin":39,"characterOffsetEnd":40,"pos":"DT","before":" ","after":" "},{"index":10,"word":"low-power-use","originalText":"low-power-use","lemma":"low-power-use","characterOffsetBegin":41,"characterOffsetEnd":54,"pos":"JJ","before":" ","after":" "},{"index":11,"word":"mode","originalText":"mode","lemma":"mode","characterOffsetBegin":55,"characterOffsetEnd":59,"pos":"NN","before":" ","after":" "},{"index":12,"word":"and","originalText":"and","lemma":"and","characterOffsetBegin":60,"characterOffsetEnd":63,"pos":"CC","before":" ","after":" "},{"index":13,"word":"if","originalText":"if","lemma":"if","characterOffsetBegin":64,"characterOffsetEnd":66,"pos":"IN","before":" ","after":""}]}]}
{"sentences":[{"index":0,"tokens":[{"index":1,"word":">>","originalText":">>","lemma":">>","characterOffsetBegin":0,"characterOffsetEnd":2,"pos":"NN","before":"","after":""},{"index":2,"word":"maybe","originalText":"maybe","lemma":"maybe","characterOffsetBegin":2,"characterOffsetEnd":7,"pos":"RB","before":"","after":" "},{"index":3,"word":"in","originalText":"in","lemma":"in","characterOffsetBegin":8,"characterOffsetEnd":10,"pos":"IN","before":" ","after":" "},{"index":4,"word":"a","originalText":"a","lemma":"a","characterOffsetBegin":11,"characterOffsetEnd":12,"pos":"DT","before":" ","after":" "},{"index":5,"word":"few","originalText":"few","lemma":"few","characterOffsetBegin":13,"characterOffsetEnd":16,"pos":"JJ","before":" ","after":" "},{"index":6,"word":"years","originalText":"years","lemma":"year","characterOffsetBegin":17,"characterOffsetEnd":22,"pos":"NNS","before":" ","after":" "},{"index":7,"word":"if","originalText":"if","lemma":"if","characterOffsetBegin":23,"characterOffsetEnd":25,"pos":"IN","before":" ","after":" "},{"index":8,"word":"funding","originalText":"funding","lemma":"funding","characterOffsetBegin":26,"characterOffsetEnd":33,"pos":"NN","before":" ","after":" "},{"index":9,"word":"gets","originalText":"gets","lemma":"get","characterOffsetBegin":34,"characterOffsetEnd":38,"pos":"VBZ","before":" ","after":" "},{"index":10,"word":"restored","originalText":"restored","lemma":"restore","characterOffsetBegin":39,"characterOffsetEnd":47,"pos":"VBN","before":" ","after":" "},{"index":11,"word":"after","originalText":"after","lemma":"after","characterOffsetBegin":48,"characterOffsetEnd":53,"pos":"IN","before":" ","after":" "},{"index":12,"word":"the","originalText":"the","lemma":"the","characterOffsetBegin":54,"characterOffsetEnd":57,"pos":"DT","before":" ","after":" "},{"index":13,"word":"economy","originalText":"economy","lemma":"economy","characterOffsetBegin":58,"characterOffsetEnd":65,"pos":"NN","before":" ","after":""}]}]}
{"sentences":[{"index":0,"tokens":[{"index":1,"word":">>","originalText":">>","lemma":">>","characterOffsetBegin":0,"characterOffsetEnd":2,"pos":"NN","before":"","after":""},{"index":2,"word":"gets","originalText":"gets","lemma":"get","characterOffsetBegin":2,"characterOffsetEnd":6,"pos":"VBZ","before":"","after":" "},{"index":3,"word":"better","originalText":"better","lemma":"better","characterOffsetBegin":7,"characterOffsetEnd":13,"pos":"JJR","before":" ","after":" "},{"index":4,"word":"-LRB-","originalText":"(","lemma":"-lrb-","characterOffsetBegin":14,"characterOffsetEnd":15,"pos":"-LRB-","before":" ","after":""},{"index":5,"word":"hopefully","originalText":"hopefully","lemma":"hopefully","characterOffsetBegin":15,"characterOffsetEnd":24,"pos":"RB","before":"","after":""},{"index":6,"word":"-RRB-","originalText":")","lemma":"-rrb-","characterOffsetBegin":24,"characterOffsetEnd":25,"pos":"-RRB-","before":"","after":""},{"index":7,"word":",","originalText":",","lemma":",","characterOffsetBegin":25,"characterOffsetEnd":26,"pos":",","before":"","after":" "},{"index":8,"word":"it","originalText":"it","lemma":"it","characterOffsetBegin":27,"characterOffsetEnd":29,"pos":"PRP","before":" ","after":" "},{"index":9,"word":"could","originalText":"could","lemma":"could","characterOffsetBegin":30,"characterOffsetEnd":35,"pos":"MD","before":" ","after":" "},{"index":10,"word":"be","originalText":"be","lemma":"be","characterOffsetBegin":36,"characterOffsetEnd":38,"pos":"VB","before":" ","after":" "},{"index":11,"word":"turned","originalText":"turned","lemma":"turn","characterOffsetBegin":39,"characterOffsetEnd":45,"pos":"VBN","before":" ","after":" "},{"index":12,"word":"on","originalText":"on","lemma":"on","characterOffsetBegin":46,"characterOffsetEnd":48,"pos":"RP","before":" ","after":" "},{"index":13,"word":"again","originalText":"again","lemma":"again","characterOffsetBegin":49,"characterOffsetEnd":54,"pos":"RB","before":" ","after":""},{"index":14,"word":".","originalText":".","lemma":".","characterOffsetBegin":54,"characterOffsetEnd":55,"pos":".","before":"","after":""}]}]}
{"sentences":[{"index":0,"tokens":[{"index":1,"word":">","originalText":">","lemma":">","characterOffsetBegin":0,"characterOffsetEnd":1,"pos":"JJR","before":"","after":""}]}]}
{"sentences":[{"index":0,"tokens":[{"index":1,"word":">","originalText":">","lemma":">","characterOffsetBegin":0,"characterOffsetEnd":1,"pos":"JJR","before":"","after":""},{"index":2,"word":"It","originalText":"It","lemma":"it","characterOffsetBegin":1,"characterOffsetEnd":3,"pos":"PRP","before":"","after":" "},{"index":3,"word":"can","originalText":"can","lemma":"can","characterOffsetBegin":4,"characterOffsetEnd":7,"pos":"MD","before":" ","after":" "},{"index":4,"word":"be","originalText":"be","lemma":"be","characterOffsetBegin":8,"characterOffsetEnd":10,"pos":"VB","before":" ","after":""},{"index":5,"word":",","originalText":",","lemma":",","characterOffsetBegin":10,"characterOffsetEnd":11,"pos":",","before":"","after":" "},{"index":6,"word":"but","originalText":"but","lemma":"but","characterOffsetBegin":12,"characterOffsetEnd":15,"pos":"CC","before":" ","after":" "},{"index":7,"word":"the","originalText":"the","lemma":"the","characterOffsetBegin":16,"characterOffsetEnd":19,"pos":"DT","before":" ","after":" "},{"index":8,"word":"problem","originalText":"problem","lemma":"problem","characterOffsetBegin":20,"characterOffsetEnd":27,"pos":"NN","before":" ","after":" "},{"index":9,"word":"is","originalText":"is","lemma":"be","characterOffsetBegin":28,"characterOffsetEnd":30,"pos":"VBZ","before":" ","after":" "},{"index":10,"word":"a","originalText":"a","lemma":"a","characterOffsetBegin":31,"characterOffsetEnd":32,"pos":"DT","before":" ","after":" "},{"index":11,"word":"political","originalText":"political","lemma":"political","characterOffsetBegin":33,"characterOffsetEnd":42,"pos":"JJ","before":" ","after":" "},{"index":12,"word":"one","originalText":"one","lemma":"one","characterOffsetBegin":43,"characterOffsetEnd":46,"pos":"CD","before":" ","after":""},{"index":13,"word":",","originalText":",","lemma":",","characterOffsetBegin":46,"characterOffsetEnd":47,"pos":",","before":"","after":" "},{"index":14,"word":"not","originalText":"not","lemma":"not","characterOffsetBegin":48,"characterOffsetEnd":51,"pos":"RB","before":" ","after":" "},{"index":15,"word":"a","originalText":"a","lemma":"a","characterOffsetBegin":52,"characterOffsetEnd":53,"pos":"DT","before":" ","after":" "},{"index":16,"word":"technical","originalText":"technical","lemma":"technical","characterOffsetBegin":54,"characterOffsetEnd":63,"pos":"JJ","before":" ","after":" "},{"index":17,"word":"one","originalText":"one","lemma":"one","characterOffsetBegin":64,"characterOffsetEnd":67,"pos":"CD","before":" ","after":""},{"index":18,"word":".","originalText":".","lemma":".","characterOffsetBegin":67,"characterOffsetEnd":68,"pos":".","before":"","after":""}]}]}
{"sentences":[]}
{"sentences":[{"index":0,"tokens":[{"index":1,"word":"Also","originalText":"Also","lemma":"also","characterOffsetBegin":0,"characterOffsetEnd":4,"pos":"RB","before":"","after":" "},{"index":2,"word":"remember","originalText":"remember","lemma":"remember","characterOffsetBegin":5,"characterOffsetEnd":13,"pos":"VBP","before":" ","after":" "},{"index":3,"word":"that","originalText":"that","lemma":"that","characterOffsetBegin":14,"characterOffsetEnd":18,"pos":"IN","before":" ","after":" "},{"index":4,"word":"every","originalText":"every","lemma":"every","characterOffsetBegin":19,"characterOffsetEnd":24,"pos":"DT","before":" ","after":" "},{"index":5,"word":"dollar","originalText":"dollar","lemma":"dollar","characterOffsetBegin":25,"characterOffsetEnd":31,"pos":"NN","before":" ","after":" "},{"index":6,"word":"spent","originalText":"spent","lemma":"spend","characterOffsetBegin":32,"characterOffsetEnd":37,"pos":"VBD","before":" ","after":" "},{"index":7,"word":"keeping","originalText":"keeping","lemma":"keep","characterOffsetBegin":38,"characterOffsetEnd":45,"pos":"VBG","before":" ","after":" "},{"index":8,"word":"one","originalText":"one","lemma":"one","characterOffsetBegin":46,"characterOffsetEnd":49,"pos":"CD","before":" ","after":" "},{"index":9,"word":"spacecraft","originalText":"spacecraft","lemma":"spacecraft","characterOffsetBegin":50,"characterOffsetEnd":60,"pos":"NN","before":" ","after":" "},{"index":10,"word":"in","originalText":"in","lemma":"in","characterOffsetBegin":61,"characterOffsetEnd":63,"pos":"IN","before":" ","after":" "},{"index":11,"word":"safe","originalText":"safe","lemma":"safe","characterOffsetBegin":64,"characterOffsetEnd":68,"pos":"JJ","before":" ","after":" "},{"index":12,"word":"mode","originalText":"mode","lemma":"mode","characterOffsetBegin":69,"characterOffsetEnd":73,"pos":"NN","before":" ","after":""}]}]}
{"sentences":[{"index":0,"tokens":[{"index":1,"word":"-LRB-","originalText":"(","lemma":"-lrb-","characterOffsetBegin":0,"characterOffsetEnd":1,"pos":"-LRB-","before":"","after":""},{"index":2,"word":"probably","originalText":"probably","lemma":"probably","characterOffsetBegin":1,"characterOffsetEnd":9,"pos":"RB","before":"","after":" "},{"index":3,"word":"a","originalText":"a","lemma":"a","characterOffsetBegin":10,"characterOffsetEnd":11,"pos":"DT","before":" ","after":" "},{"index":4,"word":"spin-stabilized","originalText":"spin-stabilized","lemma":"spin-stabilized","characterOffsetBegin":12,"characterOffsetEnd":27,"pos":"JJ","before":" ","after":" "},{"index":5,"word":"sun-pointing","originalText":"sun-pointing","lemma":"sun-pointing","characterOffsetBegin":28,"characterOffsetEnd":40,"pos":"JJ","before":" ","after":" "},{"index":6,"word":"orientation","originalText":"orientation","lemma":"orientation","characterOffsetBegin":41,"characterOffsetEnd":52,"pos":"NN","before":" ","after":""},{"index":7,"word":"-RRB-","originalText":")","lemma":"-rrb-","characterOffsetBegin":52,"characterOffsetEnd":53,"pos":"-RRB-","before":"","after":" "},{"index":8,"word":"is","originalText":"is","lemma":"be","characterOffsetBegin":54,"characterOffsetEnd":56,"pos":"VBZ","before":" ","after":" "},{"index":9,"word":"a","originalText":"a","lemma":"a","characterOffsetBegin":57,"characterOffsetEnd":58,"pos":"DT","before":" ","after":" "},{"index":10,"word":"dollar","originalText":"dollar","lemma":"dollar","characterOffsetBegin":59,"characterOffsetEnd":65,"pos":"NN","before":" ","after":" "},{"index":11,"word":"not","originalText":"not","lemma":"not","characterOffsetBegin":66,"characterOffsetEnd":69,"pos":"RB","before":" ","after":""}]}]}
{"sentences":[{"index":0,"tokens":[{"index":1,"word":"spent","originalText":"spent","lemma":"spend","characterOffsetBegin":0,"characterOffsetEnd":5,"pos":"VBN","before":"","after":" "},{"index":2,"word":"on","originalText":"on","lemma":"on","characterOffsetBegin":6,"characterOffsetEnd":8,"pos":"IN","before":" ","after":" "},{"index":3,"word":"mission","originalText":"mission","lemma":"mission","characterOffsetBegin":9,"characterOffsetEnd":16,"pos":"NN","before":" ","after":" "},{"index":4,"word":"analysis","originalText":"analysis","lemma":"analysis","characterOffsetBegin":17,"characterOffsetEnd":25,"pos":"NN","before":" ","after":" "},{"index":5,"word":"for","originalText":"for","lemma":"for","characterOffsetBegin":26,"characterOffsetEnd":29,"pos":"IN","before":" ","after":" "},{"index":6,"word":"a","originalText":"a","lemma":"a","characterOffsetBegin":30,"characterOffsetEnd":31,"pos":"DT","before":" ","after":" "},{"index":7,"word":"newer","originalText":"newer","lemma":"newer","characterOffsetBegin":32,"characterOffsetEnd":37,"pos":"JJR","before":" ","after":" "},{"index":8,"word":"spacecraft","originalText":"spacecraft","lemma":"spacecraft","characterOffsetBegin":38,"characterOffsetEnd":48,"pos":"NN","before":" ","after":""},{"index":9,"word":".","originalText":".","lemma":".","characterOffsetBegin":48,"characterOffsetEnd":49,"pos":".","before":"","after":"  "}]},{"index":1,"tokens":[{"index":1,"word":"In","originalText":"In","lemma":"in","characterOffsetBegin":51,"characterOffsetEnd":53,"pos":"IN","before":"  ","after":" "},{"index":2,"word":"order","originalText":"order","lemma":"order","characterOffsetBegin":54,"characterOffsetEnd":59,"pos":"NN","before":" ","after":" "},{"index":3,"word":"to","originalText":"to","lemma":"to","characterOffsetBegin":60,"characterOffsetEnd":62,"pos":"TO","before":" ","after":" "},{"index":4,"word":"turn","originalText":"turn","lemma":"turn","characterOffsetBegin":63,"characterOffsetEnd":67,"pos":"VB","before":" ","after":" "},{"index":5,"word":"the","originalText":"the","lemma":"the","characterOffsetBegin":68,"characterOffsetEnd":71,"pos":"DT","before":" ","after":""}]}]}
{"sentences":[{"index":0,"tokens":[{"index":1,"word":"spacecraft","originalText":"spacecraft","lemma":"spacecraft","characterOffsetBegin":0,"characterOffsetEnd":10,"pos":"NN","before":"","after":" "},{"index":2,"word":"back","originalText":"back","lemma":"back","characterOffsetBegin":11,"characterOffsetEnd":15,"pos":"RB","before":" ","after":" "},{"index":3,"word":"on","originalText":"on","lemma":"on","characterOffsetBegin":16,"characterOffsetEnd":18,"pos":"IN","before":" ","after":""},{"index":4,"word":",","originalText":",","lemma":",","characterOffsetBegin":18,"characterOffsetEnd":19,"pos":",","before":"","after":" "},{"index":5,"word":"you","originalText":"you","lemma":"you","characterOffsetBegin":20,"characterOffsetEnd":23,"pos":"PRP","before":" ","after":" "},{"index":6,"word":"either","originalText":"either","lemma":"either","characterOffsetBegin":24,"characterOffsetEnd":30,"pos":"RB","before":" ","after":" "},{"index":7,"word":"need","originalText":"need","lemma":"need","characterOffsetBegin":31,"characterOffsetEnd":35,"pos":"VBP","before":" ","after":" "},{"index":8,"word":"to","originalText":"to","lemma":"to","characterOffsetBegin":36,"characterOffsetEnd":38,"pos":"TO","before":" ","after":" "},{"index":9,"word":"insure","originalText":"insure","lemma":"insure","characterOffsetBegin":39,"characterOffsetEnd":45,"pos":"VB","before":" ","after":" "},{"index":10,"word":"that","originalText":"that","lemma":"that","characterOffsetBegin":46,"characterOffsetEnd":50,"pos":"IN","before":" ","after":" "},{"index":11,"word":"the","originalText":"the","lemma":"the","characterOffsetBegin":51,"characterOffsetEnd":54,"pos":"DT","before":" ","after":" "},{"index":12,"word":"Ops","originalText":"Ops","lemma":"Ops","characterOffsetBegin":55,"characterOffsetEnd":58,"pos":"NNP","before":" ","after":" "},{"index":13,"word":"guys","originalText":"guys","lemma":"guy","characterOffsetBegin":59,"characterOffsetEnd":63,"pos":"NNS","before":" ","after":" "},{"index":14,"word":"will","originalText":"will","lemma":"will","characterOffsetBegin":64,"characterOffsetEnd":68,"pos":"MD","before":" ","after":" "},{"index":15,"word":"be","originalText":"be","lemma":"be","characterOffsetBegin":69,"characterOffsetEnd":71,"pos":"VB","before":" ","after":""}]}]}
{"sentences":[{"index":0,"tokens":[{"index":1,"word":"available","originalText":"available","lemma":"available","characterOffsetBegin":0,"characterOffsetEnd":9,"pos":"JJ","before":"","after":""},{"index":2,"word":",","originalText":",","lemma":",","characterOffsetBegin":9,"characterOffsetEnd":10,"pos":",","before":"","after":" "},{"index":3,"word":"or","originalText":"or","lemma":"or","characterOffsetBegin":11,"characterOffsetEnd":13,"pos":"CC","before":" ","after":" "},{"index":4,"word":"you","originalText":"you","lemma":"you","characterOffsetBegin":14,"characterOffsetEnd":17,"pos":"PRP","before":" ","after":" "},{"index":5,"word":"need","originalText":"need","lemma":"need","characterOffsetBegin":18,"characterOffsetEnd":22,"pos":"VBP","before":" ","after":" "},{"index":6,"word":"to","originalText":"to","lemma":"to","characterOffsetBegin":23,"characterOffsetEnd":25,"pos":"TO","before":" ","after":" "},{"index":7,"word":"retrain","originalText":"retrain","lemma":"retrain","characterOffsetBegin":26,"characterOffsetEnd":33,"pos":"VB","before":" ","after":" "},{"index":8,"word":"a","originalText":"a","lemma":"a","characterOffsetBegin":34,"characterOffsetEnd":35,"pos":"DT","before":" ","after":" "},{"index":9,"word":"new","originalText":"new","lemma":"new","characterOffsetBegin":36,"characterOffsetEnd":39,"pos":"JJ","before":" ","after":" "},{"index":10,"word":"team","originalText":"team","lemma":"team","characterOffsetBegin":40,"characterOffsetEnd":44,"pos":"NN","before":" ","after":""},{"index":11,"word":".","originalText":".","lemma":".","characterOffsetBegin":44,"characterOffsetEnd":45,"pos":".","before":"","after":""}]}]}
{"sentences":[]}
{"sentences":[{"index":0,"tokens":[{"index":1,"word":"Having","originalText":"Having","lemma":"have","characterOffsetBegin":0,"characterOffsetEnd":6,"pos":"VBG","before":"","after":" "},{"index":2,"word":"said","originalText":"said","lemma":"say","characterOffsetBegin":7,"characterOffsetEnd":11,"pos":"VBD","before":" ","after":" "},{"index":3,"word":"that","originalText":"that","lemma":"that","characterOffsetBegin":12,"characterOffsetEnd":16,"pos":"IN","before":" ","after":""},{"index":4,"word":",","originalText":",","lemma":",","characterOffsetBegin":16,"characterOffsetEnd":17,"pos":",","before":"","after":" "},{"index":5,"word":"there","originalText":"there","lemma":"there","characterOffsetBegin":18,"characterOffsetEnd":23,"pos":"EX","before":" ","after":" "},{"index":6,"word":"are","originalText":"are","lemma":"be","characterOffsetBegin":24,"characterOffsetEnd":27,"pos":"VBP","before":" ","after":" "},{"index":7,"word":"some","originalText":"some","lemma":"some","characterOffsetBegin":28,"characterOffsetEnd":32,"pos":"DT","before":" ","after":" "},{"index":8,"word":"spacecraft","originalText":"spacecraft","lemma":"spacecraft","characterOffsetBegin":33,"characterOffsetEnd":43,"pos":"NN","before":" ","after":" "},{"index":9,"word":"that","originalText":"that","lemma":"that","characterOffsetBegin":44,"characterOffsetEnd":48,"pos":"WDT","before":" ","after":" "},{"index":10,"word":"do","originalText":"do","lemma":"do","characterOffsetBegin":49,"characterOffsetEnd":51,"pos":"VBP","before":" ","after":" "},{"index":11,"word":"what","originalText":"what","lemma":"what","characterOffsetBegin":52,"characterOffsetEnd":56,"pos":"WP","before":" ","after":" "},{"index":12,"word":"you","originalText":"you","lemma":"you","characterOffsetBegin":57,"characterOffsetEnd":60,"pos":"PRP","before":" ","after":" "},{"index":13,"word":"have","originalText":"have","lemma":"have","characterOffsetBegin":61,"characterOffsetEnd":65,"pos":"VBP","before":" ","after":" "},{"index":14,"word":"proposed","originalText":"proposed","lemma":"propose","characterOffsetBegin":66,"characterOffsetEnd":74,"pos":"VBN","before":" ","after":""},{"index":15,"word":".","originalText":".","lemma":".","characterOffsetBegin":74,"characterOffsetEnd":75,"pos":".","before":"","after":""}]}]}
{"sentences":[{"index":0,"tokens":[{"index":1,"word":"Many","originalText":"Many","lemma":"many","characterOffsetBegin":0,"characterOffsetEnd":4,"pos":"JJ","before":"","after":" "},{"index":2,"word":"of","originalText":"of","lemma":"of","characterOffsetBegin":5,"characterOffsetEnd":7,"pos":"IN","before":" ","after":" "},{"index":3,"word":"the","originalText":"the","lemma":"the","characterOffsetBegin":8,"characterOffsetEnd":11,"pos":"DT","before":" ","after":" "},{"index":4,"word":"operational","originalText":"operational","lemma":"operational","characterOffsetBegin":12,"characterOffsetEnd":23,"pos":"JJ","before":" ","after":" "},{"index":5,"word":"satellites","originalText":"satellites","lemma":"satellite","characterOffsetBegin":24,"characterOffsetEnd":34,"pos":"NNS","before":" ","after":" "},{"index":6,"word":"Goddard","originalText":"Goddard","lemma":"Goddard","characterOffsetBegin":35,"characterOffsetEnd":42,"pos":"NNP","before":" ","after":" "},{"index":7,"word":"flies","originalText":"flies","lemma":"fly","characterOffsetBegin":43,"characterOffsetEnd":48,"pos":"VBZ","before":" ","after":" "},{"index":8,"word":"-LRB-","originalText":"(","lemma":"-lrb-","characterOffsetBegin":49,"characterOffsetEnd":50,"pos":"-LRB-","before":" ","after":""},{"index":9,"word":"like","originalText":"like","lemma":"like","characterOffsetBegin":50,"characterOffsetEnd":54,"pos":"IN","before":"","after":" "},{"index":10,"word":"the","originalText":"the","lemma":"the","characterOffsetBegin":55,"characterOffsetEnd":58,"pos":"DT","before":" ","after":" "},{"index":11,"word":"Tiros","originalText":"Tiros","lemma":"Tiros","characterOffsetBegin":59,"characterOffsetEnd":64,"pos":"NNP","before":" ","after":" "},{"index":12,"word":"NOAA","originalText":"NOAA","lemma":"NOAA","characterOffsetBegin":65,"characterOffsetEnd":69,"pos":"NNP","before":" ","after":""}]}]}
{"sentences":[{"index":0,"tokens":[{"index":1,"word":"series","originalText":"series","lemma":"series","characterOffsetBegin":0,"characterOffsetEnd":6,"pos":"NN","before":"","after":""},{"index":2,"word":"-RRB-","originalText":")","lemma":"-rrb-","characterOffsetBegin":6,"characterOffsetEnd":7,"pos":"-RRB-","before":"","after":" "},{"index":3,"word":"require","originalText":"require","lemma":"require","characterOffsetBegin":8,"characterOffsetEnd":15,"pos":"VBP","before":" ","after":" "},{"index":4,"word":"more","originalText":"more","lemma":"more","characterOffsetBegin":16,"characterOffsetEnd":20,"pos":"JJR","before":" ","after":" "},{"index":5,"word":"than","originalText":"than","lemma":"than","characterOffsetBegin":21,"characterOffsetEnd":25,"pos":"IN","before":" ","after":" "},{"index":6,"word":"one","originalText":"one","lemma":"one","characterOffsetBegin":26,"characterOffsetEnd":29,"pos":"CD","before":" ","after":" "},{"index":7,"word":"satellite","originalText":"satellite","lemma":"satellite","characterOffsetBegin":30,"characterOffsetEnd":39,"pos":"NN","before":" ","after":" "},{"index":8,"word":"in","originalText":"in","lemma":"in","characterOffsetBegin":40,"characterOffsetEnd":42,"pos":"IN","before":" ","after":" "},{"index":9,"word":"orbit","originalText":"orbit","lemma":"orbit","characterOffsetBegin":43,"characterOffsetEnd":48,"pos":"NN","before":" ","after":" "},{"index":10,"word":"for","originalText":"for","lemma":"for","characterOffsetBegin":49,"characterOffsetEnd":52,"pos":"IN","before":" ","after":" "},{"index":11,"word":"an","originalText":"an","lemma":"a","characterOffsetBegin":53,"characterOffsetEnd":55,"pos":"DT","before":" ","after":" "},{"index":12,"word":"operational","originalText":"operational","lemma":"operational","characterOffsetBegin":56,"characterOffsetEnd":67,"pos":"JJ","before":" ","after":" "},{"index":13,"word":"set","originalText":"set","lemma":"set","characterOffsetBegin":68,"characterOffsetEnd":71,"pos":"NN","before":" ","after":""},{"index":14,"word":".","originalText":".","lemma":".","characterOffsetBegin":71,"characterOffsetEnd":72,"pos":".","before":"","after":""}]}]}
{"sentences":[{"index":0,"tokens":[{"index":1,"word":"Extras","originalText":"Extras","lemma":"extra","characterOffsetBegin":0,"characterOffsetEnd":6,"pos":"NNS","before":"","after":" "},{"index":2,"word":"which","originalText":"which","lemma":"which","characterOffsetBegin":7,"characterOffsetEnd":12,"pos":"WDT","before":" ","after":" "},{"index":3,"word":"get","originalText":"get","lemma":"get","characterOffsetBegin":13,"characterOffsetEnd":16,"pos":"VBP","before":" ","after":" "},{"index":4,"word":"replaced","originalText":"replaced","lemma":"replace","characterOffsetBegin":17,"characterOffsetEnd":25,"pos":"VBN","before":" ","after":" "},{"index":5,"word":"on-orbit","originalText":"on-orbit","lemma":"on-orbit","characterOffsetBegin":26,"characterOffsetEnd":34,"pos":"JJ","before":" ","after":" "},{"index":6,"word":"are","originalText":"are","lemma":"be","characterOffsetBegin":35,"characterOffsetEnd":38,"pos":"VBP","before":" ","after":" "},{"index":7,"word":"powered","originalText":"powered","lemma":"power","characterOffsetBegin":39,"characterOffsetEnd":46,"pos":"VBN","before":" ","after":" "},{"index":8,"word":"into","originalText":"into","lemma":"into","characterOffsetBegin":47,"characterOffsetEnd":51,"pos":"IN","before":" ","after":" "},{"index":9,"word":"a","originalText":"a","lemma":"a","characterOffsetBegin":52,"characterOffsetEnd":53,"pos":"DT","before":" ","after":" "},{"index":10,"word":"``","originalText":"\"","lemma":"``","characterOffsetBegin":54,"characterOffsetEnd":55,"pos":"``","before":" ","after":""},{"index":11,"word":"standby","originalText":"standby","lemma":"standby","characterOffsetBegin":55,"characterOffsetEnd":62,"pos":"NN","before":"","after":""},{"index":12,"word":"''","originalText":"\"","lemma":"''","characterOffsetBegin":62,"characterOffsetEnd":63,"pos":"''","before":"","after":" "},{"index":13,"word":"mode","originalText":"mode","lemma":"mode","characterOffsetBegin":64,"characterOffsetEnd":68,"pos":"NN","before":" ","after":" "},{"index":14,"word":"for","originalText":"for","lemma":"for","characterOffsetBegin":69,"characterOffsetEnd":72,"pos":"IN","before":" ","after":""}]}]}
{"sentences":[{"index":0,"tokens":[{"index":1,"word":"use","originalText":"use","lemma":"use","characterOffsetBegin":0,"characterOffsetEnd":3,"pos":"NN","before":"","after":" "},{"index":2,"word":"in","originalText":"in","lemma":"in","characterOffsetBegin":4,"characterOffsetEnd":6,"pos":"IN","before":" ","after":" "},{"index":3,"word":"an","originalText":"an","lemma":"a","characterOffsetBegin":7,"characterOffsetEnd":9,"pos":"DT","before":" ","after":" "},{"index":4,"word":"emergency","originalText":"emergency","lemma":"emergency","characterOffsetBegin":10,"characterOffsetEnd":19,"pos":"NN","before":" ","after":""},{"index":5,"word":".","originalText":".","lemma":".","characterOffsetBegin":19,"characterOffsetEnd":20,"pos":".","before":"","after":"  "}]},{"index":1,"tokens":[{"index":1,"word":"In","originalText":"In","lemma":"in","characterOffsetBegin":22,"characterOffsetEnd":24,"pos":"IN","before":"  ","after":" "},{"index":2,"word":"that","originalText":"that","lemma":"that","characterOffsetBegin":25,"characterOffsetEnd":29,"pos":"DT","before":" ","after":" "},{"index":3,"word":"case","originalText":"case","lemma":"case","characterOffsetBegin":30,"characterOffsetEnd":34,"pos":"NN","before":" ","after":""},{"index":4,"word":",","originalText":",","lemma":",","characterOffsetBegin":34,"characterOffsetEnd":35,"pos":",","before":"","after":" "},{"index":5,"word":"however","originalText":"however","lemma":"however","characterOffsetBegin":36,"characterOffsetEnd":43,"pos":"RB","before":" ","after":""},{"index":6,"word":",","originalText":",","lemma":",","characterOffsetBegin":43,"characterOffsetEnd":44,"pos":",","before":"","after":" "},{"index":7,"word":"the","originalText":"the","lemma":"the","characterOffsetBegin":45,"characterOffsetEnd":48,"pos":"DT","before":" ","after":" "},{"index":8,"word":"same","originalText":"same","lemma":"same","characterOffsetBegin":49,"characterOffsetEnd":53,"pos":"JJ","before":" ","after":" "},{"index":9,"word":"ops","originalText":"ops","lemma":"op","characterOffsetBegin":54,"characterOffsetEnd":57,"pos":"NNS","before":" ","after":" "},{"index":10,"word":"team","originalText":"team","lemma":"team","characterOffsetBegin":58,"characterOffsetEnd":62,"pos":"NN","before":" ","after":" "},{"index":11,"word":"is","originalText":"is","lemma":"be","characterOffsetBegin":63,"characterOffsetEnd":65,"pos":"VBZ","before":" ","after":" "},{"index":12,"word":"still","originalText":"still","lemma":"still","characterOffsetBegin":66,"characterOffsetEnd":71,"pos":"RB","before":" ","after":""}]}]}
{"sentences":[{"index":0,"tokens":[{"index":1,"word":"required","originalText":"required","lemma":"require","characterOffsetBegin":0,"characterOffsetEnd":8,"pos":"VBN","before":"","after":" "},{"index":2,"word":"to","originalText":"to","lemma":"to","characterOffsetBegin":9,"characterOffsetEnd":11,"pos":"TO","before":" ","after":" "},{"index":3,"word":"fly","originalText":"fly","lemma":"fly","characterOffsetBegin":12,"characterOffsetEnd":15,"pos":"VB","before":" ","after":" "},{"index":4,"word":"the","originalText":"the","lemma":"the","characterOffsetBegin":16,"characterOffsetEnd":19,"pos":"DT","before":" ","after":" "},{"index":5,"word":"operational","originalText":"operational","lemma":"operational","characterOffsetBegin":20,"characterOffsetEnd":31,"pos":"JJ","before":" ","after":" "},{"index":6,"word":"birds","originalText":"birds","lemma":"bird","characterOffsetBegin":32,"characterOffsetEnd":37,"pos":"NNS","before":" ","after":""},{"index":7,"word":";","originalText":";","lemma":";","characterOffsetBegin":37,"characterOffsetEnd":38,"pos":":","before":"","after":" "},{"index":8,"word":"so","originalText":"so","lemma":"so","characterOffsetBegin":39,"characterOffsetEnd":41,"pos":"RB","before":" ","after":" "},{"index":9,"word":"the","originalText":"the","lemma":"the","characterOffsetBegin":42,"characterOffsetEnd":45,"pos":"DT","before":" ","after":" "},{"index":10,"word":"standby","originalText":"standby","lemma":"standby","characterOffsetBegin":46,"characterOffsetEnd":53,"pos":"JJ","before":" ","after":" "},{"index":11,"word":"maintenance","originalText":"maintenance","lemma":"maintenance","characterOffsetBegin":54,"characterOffsetEnd":65,"pos":"NN","before":" ","after":" "},{"index":12,"word":"is","originalText":"is","lemma":"be","characterOffsetBegin":66,"characterOffsetEnd":68,"pos":"VBZ","before":" ","after":""}]}]}
{"sentences":[{"index":0,"tokens":[{"index":1,"word":"relatively","originalText":"relatively","lemma":"relatively","characterOffsetBegin":0,"characterOffsetEnd":10,"pos":"RB","before":"","after":" "},{"index":2,"word":"cheap","originalText":"cheap","lemma":"cheap","characterOffsetBegin":11,"characterOffsetEnd":16,"pos":"JJ","before":" ","after":""},{"index":3,"word":".","originalText":".","lemma":".","characterOffsetBegin":16,"characterOffsetEnd":17,"pos":".","before":"","after":""}]}]}
{"sentences":[]}
{"sentences":[{"index":0,"tokens":[{"index":1,"word":"Finally","originalText":"Finally","lemma":"finally","characterOffsetBegin":0,"characterOffsetEnd":7,"pos":"RB","before":"","after":""},{"index":2,"word":",","originalText":",","lemma":",","characterOffsetBegin":7,"characterOffsetEnd":8,"pos":",","before":"","after":" "},{"index":3,"word":"Pat","originalText":"Pat","lemma":"Pat","characterOffsetBegin":9,"characterOffsetEnd":12,"pos":"NNP","before":" ","after":""},{"index":4,"word":"'s","originalText":"'s","lemma":"'s","characterOffsetBegin":12,"characterOffsetEnd":14,"pos":"POS","before":"","after":" "},{"index":5,"word":"explanation","originalText":"explanation","lemma":"explanation","characterOffsetBegin":15,"characterOffsetEnd":26,"pos":"NN","before":" ","after":" "},{"index":6,"word":"-LRB-","originalText":"(","lemma":"-lrb-","characterOffsetBegin":27,"characterOffsetEnd":28,"pos":"-LRB-","before":" ","after":""},{"index":7,"word":"some","originalText":"some","lemma":"some","characterOffsetBegin":28,"characterOffsetEnd":32,"pos":"DT","before":"","after":" "},{"index":8,"word":"spacecraft","originalText":"spacecraft","lemma":"spacecraft","characterOffsetBegin":33,"characterOffsetEnd":43,"pos":"NN","before":" ","after":" "},{"index":9,"word":"require","originalText":"require","lemma":"require","characterOffsetBegin":44,"characterOffsetEnd":51,"pos":"VBP","before":" ","after":" "},{"index":10,"word":"continuous","originalText":"continuous","lemma":"continuous","characterOffsetBegin":52,"characterOffsetEnd":62,"pos":"JJ","before":" ","after":" "},{"index":11,"word":"maintenance","originalText":"maintenance","lemma":"maintenance","characterOffsetBegin":63,"characterOffsetEnd":74,"pos":"NN","before":" ","after":""}]}]}
{"sentences":[{"index":0,"tokens":[{"index":1,"word":"to","originalText":"to","lemma":"to","characterOffsetBegin":0,"characterOffsetEnd":2,"pos":"TO","before":"","after":" "},{"index":2,"word":"stay","originalText":"stay","lemma":"stay","characterOffsetBegin":3,"characterOffsetEnd":7,"pos":"VB","before":" ","after":" "},{"index":3,"word":"under","originalText":"under","lemma":"under","characterOffsetBegin":8,"characterOffsetEnd":13,"pos":"IN","before":" ","after":" "},{"index":4,"word":"control","originalText":"control","lemma":"control","characterOffsetBegin":14,"characterOffsetEnd":21,"pos":"NN","before":" ","after":""},{"index":5,"word":"-RRB-","originalText":")","lemma":"-rrb-","characterOffsetBegin":21,"characterOffsetEnd":22,"pos":"-RRB-","before":"","after":" "},{"index":6,"word":"is","originalText":"is","lemma":"be","characterOffsetBegin":23,"characterOffsetEnd":25,"pos":"VBZ","before":" ","after":" "},{"index":7,"word":"also","originalText":"also","lemma":"also","characterOffsetBegin":26,"characterOffsetEnd":30,"pos":"RB","before":" ","after":" "},{"index":8,"word":"right","originalText":"right","lemma":"right","characterOffsetBegin":31,"characterOffsetEnd":36,"pos":"JJ","before":" ","after":" "},{"index":9,"word":"on","originalText":"on","lemma":"on","characterOffsetBegin":37,"characterOffsetEnd":39,"pos":"IN","before":" ","after":" "},{"index":10,"word":"the","originalText":"the","lemma":"the","characterOffsetBegin":40,"characterOffsetEnd":43,"pos":"DT","before":" ","after":" "},{"index":11,"word":"mark","originalText":"mark","lemma":"mark","characterOffsetBegin":44,"characterOffsetEnd":48,"pos":"NN","before":" ","after":""},{"index":12,"word":".","originalText":".","lemma":".","characterOffsetBegin":48,"characterOffsetEnd":49,"pos":".","before":"","after":"  "}]},{"index":1,"tokens":[{"index":1,"word":"I","originalText":"I","lemma":"I","characterOffsetBegin":51,"characterOffsetEnd":52,"pos":"PRP","before":"  ","after":" "},{"index":2,"word":"suggested","originalText":"suggested","lemma":"suggest","characterOffsetBegin":53,"characterOffsetEnd":62,"pos":"VBD","before":" ","after":" "},{"index":3,"word":"a","originalText":"a","lemma":"a","characterOffsetBegin":63,"characterOffsetEnd":64,"pos":"DT","before":" ","after":" "},{"index":4,"word":"spin","originalText":"spin","lemma":"spin","characterOffsetBegin":65,"characterOffsetEnd":69,"pos":"NN","before":" ","after":""},{"index":5,"word":"-","originalText":"-","lemma":"-","characterOffsetBegin":69,"characterOffsetEnd":70,"pos":":","before":"","after":""}]}]}
{"sentences":[{"index":0,"tokens":[{"index":1,"word":"stabilized","originalText":"stabilized","lemma":"stabilize","characterOffsetBegin":0,"characterOffsetEnd":10,"pos":"VBN","before":"","after":" "},{"index":2,"word":"control","originalText":"control","lemma":"control","characterOffsetBegin":11,"characterOffsetEnd":18,"pos":"NN","before":" ","after":" "},{"index":3,"word":"mode","originalText":"mode","lemma":"mode","characterOffsetBegin":19,"characterOffsetEnd":23,"pos":"NN","before":" ","after":" "},{"index":4,"word":"because","originalText":"because","lemma":"because","characterOffsetBegin":24,"characterOffsetEnd":31,"pos":"IN","before":" ","after":" "},{"index":5,"word":"it","originalText":"it","lemma":"it","characterOffsetBegin":32,"characterOffsetEnd":34,"pos":"PRP","before":" ","after":" "},{"index":6,"word":"would","originalText":"would","lemma":"would","characterOffsetBegin":35,"characterOffsetEnd":40,"pos":"MD","before":" ","after":" "},{"index":7,"word":"require","originalText":"require","lemma":"require","characterOffsetBegin":41,"characterOffsetEnd":48,"pos":"VB","before":" ","after":" "},{"index":8,"word":"little","originalText":"little","lemma":"little","characterOffsetBegin":49,"characterOffsetEnd":55,"pos":"JJ","before":" ","after":" "},{"index":9,"word":"power","originalText":"power","lemma":"power","characterOffsetBegin":56,"characterOffsetEnd":61,"pos":"NN","before":" ","after":" "},{"index":10,"word":"or","originalText":"or","lemma":"or","characterOffsetBegin":62,"characterOffsetEnd":64,"pos":"CC","before":" ","after":""}]}]}
{"sentences":[{"index":0,"tokens":[{"index":1,"word":"maintenance","originalText":"maintenance","lemma":"maintenance","characterOffsetBegin":0,"characterOffsetEnd":11,"pos":"NN","before":"","after":""},{"index":2,"word":",","originalText":",","lemma":",","characterOffsetBegin":11,"characterOffsetEnd":12,"pos":",","before":"","after":" "},{"index":3,"word":"but","originalText":"but","lemma":"but","characterOffsetBegin":13,"characterOffsetEnd":16,"pos":"CC","before":" ","after":" "},{"index":4,"word":"it","originalText":"it","lemma":"it","characterOffsetBegin":17,"characterOffsetEnd":19,"pos":"PRP","before":" ","after":" "},{"index":5,"word":"still","originalText":"still","lemma":"still","characterOffsetBegin":20,"characterOffsetEnd":25,"pos":"RB","before":" ","after":" "},{"index":6,"word":"might","originalText":"might","lemma":"might","characterOffsetBegin":26,"characterOffsetEnd":31,"pos":"MD","before":" ","after":" "},{"index":7,"word":"require","originalText":"require","lemma":"require","characterOffsetBegin":32,"characterOffsetEnd":39,"pos":"VB","before":" ","after":" "},{"index":8,"word":"some","originalText":"some","lemma":"some","characterOffsetBegin":40,"characterOffsetEnd":44,"pos":"DT","before":" ","after":" "},{"index":9,"word":"momentum","originalText":"momentum","lemma":"momentum","characterOffsetBegin":45,"characterOffsetEnd":53,"pos":"NN","before":" ","after":" "},{"index":10,"word":"dumping","originalText":"dumping","lemma":"dump","characterOffsetBegin":54,"characterOffsetEnd":61,"pos":"VBG","before":" ","after":" "},{"index":11,"word":"from","originalText":"from","lemma":"from","characterOffsetBegin":62,"characterOffsetEnd":66,"pos":"IN","before":" ","after":" "},{"index":12,"word":"time","originalText":"time","lemma":"time","characterOffsetBegin":67,"characterOffsetEnd":71,"pos":"NN","before":" ","after":""}]}]}
{"sentences":[{"index":0,"tokens":[{"index":1,"word":"to","originalText":"to","lemma":"to","characterOffsetBegin":0,"characterOffsetEnd":2,"pos":"TO","before":"","after":" "},{"index":2,"word":"time","originalText":"time","lemma":"time","characterOffsetBegin":3,"characterOffsetEnd":7,"pos":"NN","before":" ","after":""},{"index":3,"word":".","originalText":".","lemma":".","characterOffsetBegin":7,"characterOffsetEnd":8,"pos":".","before":"","after":""}]}]}
{"sentences":[]}
{"sentences":[{"index":0,"tokens":[{"index":1,"word":"In","originalText":"In","lemma":"in","characterOffsetBegin":0,"characterOffsetEnd":2,"pos":"IN","before":"","after":" "},{"index":2,"word":"the","originalText":"the","lemma":"the","characterOffsetBegin":3,"characterOffsetEnd":6,"pos":"DT","before":" ","after":" "},{"index":3,"word":"end","originalText":"end","lemma":"end","characterOffsetBegin":7,"characterOffsetEnd":10,"pos":"NN","before":" ","after":""},{"index":4,"word":",","originalText":",","lemma":",","characterOffsetBegin":10,"characterOffsetEnd":11,"pos":",","before":"","after":" "},{"index":5,"word":"it","originalText":"it","lemma":"it","characterOffsetBegin":12,"characterOffsetEnd":14,"pos":"PRP","before":" ","after":" "},{"index":6,"word":"*","originalText":"*","lemma":"*","characterOffsetBegin":15,"characterOffsetEnd":16,"pos":"SYM","before":" ","after":""},{"index":7,"word":"is","originalText":"is","lemma":"be","characterOffsetBegin":16,"characterOffsetEnd":18,"pos":"VBZ","before":"","after":""},{"index":8,"word":"*","originalText":"*","lemma":"*","characterOffsetBegin":18,"characterOffsetEnd":19,"pos":"SYM","before":"","after":" "},{"index":9,"word":"a","originalText":"a","lemma":"a","characterOffsetBegin":20,"characterOffsetEnd":21,"pos":"DT","before":" ","after":" "},{"index":10,"word":"political","originalText":"political","lemma":"political","characterOffsetBegin":22,"characterOffsetEnd":31,"pos":"JJ","before":" ","after":" "},{"index":11,"word":"decision","originalText":"decision","lemma":"decision","characterOffsetBegin":32,"characterOffsetEnd":40,"pos":"NN","before":" ","after":" "},{"index":12,"word":"-LRB-","originalText":"(","lemma":"-lrb-","characterOffsetBegin":41,"characterOffsetEnd":42,"pos":"-LRB-","before":" ","after":""},{"index":13,"word":"since","originalText":"since","lemma":"since","characterOffsetBegin":42,"characterOffsetEnd":47,"pos":"IN","before":"","after":" "},{"index":14,"word":"the","originalText":"the","lemma":"the","characterOffsetBegin":48,"characterOffsetEnd":51,"pos":"DT","before":" ","after":" "},{"index":15,"word":"difference","originalText":"difference","lemma":"difference","characterOffsetBegin":52,"characterOffsetEnd":62,"pos":"NN","before":" ","after":" "},{"index":16,"word":"is","originalText":"is","lemma":"be","characterOffsetBegin":63,"characterOffsetEnd":65,"pos":"VBZ","before":" ","after":" "},{"index":17,"word":"money","originalText":"money","lemma":"money","characterOffsetBegin":66,"characterOffsetEnd":71,"pos":"NN","before":" ","after":""},{"index":18,"word":"-RRB-","originalText":")","lemma":"-rrb-","characterOffsetBegin":71,"characterOffsetEnd":72,"pos":"-RRB-","before":"","after":""},{"index":19,"word":",","originalText":",","lemma":",","characterOffsetBegin":72,"characterOffsetEnd":73,"pos":",","before":"","after":""}]}]}
{"sentences":[{"index":0,"tokens":[{"index":1,"word":"but","originalText":"but","lemma":"but","characterOffsetBegin":0,"characterOffsetEnd":3,"pos":"CC","before":"","after":" "},{"index":2,"word":"there","originalText":"there","lemma":"there","characterOffsetBegin":4,"characterOffsetEnd":9,"pos":"EX","before":" ","after":" "},{"index":3,"word":"is","originalText":"is","lemma":"be","characterOffsetBegin":10,"characterOffsetEnd":12,"pos":"VBZ","before":" ","after":" "},{"index":4,"word":"some","originalText":"some","lemma":"some","characterOffsetBegin":13,"characterOffsetEnd":17,"pos":"DT","before":" ","after":" "},{"index":5,"word":"technical","originalText":"technical","lemma":"technical","characterOffsetBegin":18,"characterOffsetEnd":27,"pos":"JJ","before":" ","after":" "},{"index":6,"word":"rationale","originalText":"rationale","lemma":"rationale","characterOffsetBegin":28,"characterOffsetEnd":37,"pos":"NN","before":" ","after":" "},{"index":7,"word":"behind","originalText":"behind","lemma":"behind","characterOffsetBegin":38,"characterOffsetEnd":44,"pos":"IN","before":" ","after":" "},{"index":8,"word":"the","originalText":"the","lemma":"the","characterOffsetBegin":45,"characterOffsetEnd":48,"pos":"DT","before":" ","after":" "},{"index":9,"word":"decision","originalText":"decision","lemma":"decision","characterOffsetBegin":49,"characterOffsetEnd":57,"pos":"NN","before":" ","after":""},{"index":10,"word":".","originalText":".","lemma":".","characterOffsetBegin":57,"characterOffsetEnd":58,"pos":".","before":"","after":""}]}]}
{"sentences":[]}
{"sentences":[{"index":0,"tokens":[{"index":1,"word":"David","originalText":"David","lemma":"David","characterOffsetBegin":0,"characterOffsetEnd":5,"pos":"NNP","before":"","after":" "},{"index":2,"word":"W.","originalText":"W.","lemma":"W.","characterOffsetBegin":6,"characterOffsetEnd":8,"pos":"NNP","before":" ","after":" "},{"index":3,"word":"@","originalText":"@","lemma":"@","characterOffsetBegin":9,"characterOffsetEnd":10,"pos":"IN","before":" ","after":" "},{"index":4,"word":"GSFC","originalText":"GSFC","lemma":"GSFC","characterOffsetBegin":11,"characterOffsetEnd":15,"pos":"NNP","before":" ","after":""}]}]}
