{"sentences":[{"index":0,"tokens":[{"index":1,"word":"From","originalText":"From","characterOffsetBegin":0,"characterOffsetEnd":4,"pos":"IN","before":"","after":""},{"index":2,"word":":","originalText":":","characterOffsetBegin":4,"characterOffsetEnd":5,"pos":":","before":"","after":" "},{"index":3,"word":"gmc@cthulhu.semi.harris.com","originalText":"gmc@cthulhu.semi.harris.com","characterOffsetBegin":6,"characterOffsetEnd":33,"pos":"NNP","before":" ","after":" "},{"index":4,"word":"Subject","originalText":"Subject","characterOffsetBegin":34,"characterOffsetEnd":41,"pos":"NNP","before":" ","after":""},{"index":5,"word":":","originalText":":","characterOffsetBegin":41,"characterOffsetEnd":42,"pos":":","before":"","after":" "},{"index":6,"word":"Re","originalText":"Re","characterOffsetBegin":43,"characterOffsetEnd":45,"pos":"NNP","before":" ","after":""},{"index":7,"word":":","originalText":":","characterOffsetBegin":45,"characterOffsetEnd":46,"pos":":","before":"","after":" "},{"index":8,"word":"What","originalText":"What","characterOffsetBegin":47,"characterOffsetEnd":51,"pos":"WP","before":" ","after":" "},{"index":9,"word":"is","originalText":"is","characterOffsetBegin":52,"characterOffsetEnd":54,"pos":"VBZ","before":" ","after":" "},{"index":10,"word":"Zero","originalText":"Zero","characterOffsetBegin":55,"characterOffsetEnd":59,"pos":"NNP","before":" ","after":" "},{"index":11,"word":"dB","originalText":"dB","characterOffsetBegin":60,"characterOffsetEnd":62,"pos":"NNP","before":" ","after":""},{"index":12,"word":"????","originalText":"????","characterOffsetBegin":62,"characterOffsetEnd":66,"pos":"CD","before":"","after":""}]},{"index":1,"tokens":[{"index":1,"word":"Nntp-Posting-Host","originalText":"Nntp-Posting-Host","characterOffsetBegin":66,"characterOffsetEnd":83,"pos":"NNP","before":"","after":""},{"index":2,"word":":","originalText":":","characterOffsetBegin":83,"characterOffsetEnd":84,"pos":":","before":"","after":" "},{"index":3,"word":"cthulhu.mlb.semi.harris.comOrganization","originalText":"cthulhu.mlb.semi.harris.comOrganization","characterOffsetBegin":85,"characterOffsetEnd":124,"pos":"NN","before":" ","after":""},{"index":4,"word":":","originalText":":","characterOffsetBegin":124,"characterOffsetEnd":125,"pos":":","before":"","after":" "},{"index":5,"word":"AnalogLines","originalText":"AnalogLines","characterOffsetBegin":126,"characterOffsetEnd":137,"pos":"NNS","before":" ","after":""},{"index":6,"word":":","originalText":":","characterOffsetBegin":137,"characterOffsetEnd":138,"pos":":","before":"","after":" "},{"index":7,"word":"57In","originalText":"57In","characterOffsetBegin":139,"characterOffsetEnd":143,"pos":"NN","before":" ","after":" "},{"index":8,"word":"article","originalText":"article","characterOffsetBegin":144,"characterOffsetEnd":151,"pos":"NN","before":" ","after":" "},{"index":9,"word":"<1993Apr6.132429.16154@bnr.ca>","originalText":"<1993Apr6.132429.16154@bnr.ca>","characterOffsetBegin":152,"characterOffsetEnd":182,"pos":"NN","before":" ","after":"      "},{"index":10,"word":"moffatt@bnr.ca","originalText":"moffatt@bnr.ca","characterOffsetBegin":188,"characterOffsetEnd":202,"pos":"NN","before":"      ","after":" "},{"index":11,"word":"-LRB-","originalText":"(","characterOffsetBegin":203,"characterOffsetEnd":204,"pos":"-LRB-","before":" ","after":""},{"index":12,"word":"John","originalText":"John","characterOffsetBegin":204,"characterOffsetEnd":208,"pos":"NNP","before":"","after":" "},{"index":13,"word":"Thomson","originalText":"Thomson","characterOffsetBegin":209,"characterOffsetEnd":216,"pos":"NNP","before":" ","after":""},{"index":14,"word":"-RRB-","originalText":")","characterOffsetBegin":216,"characterOffsetEnd":217,"pos":"-RRB-","before":"","after":" "},{"index":15,"word":"writes","originalText":"writes","characterOffsetBegin":218,"characterOffsetEnd":224,"pos":"VBZ","before":" ","after":""},{"index":16,"word":":","originalText":":","characterOffsetBegin":224,"characterOffsetEnd":225,"pos":":","before":"","after":" "},{"index":17,"word":">","originalText":">","characterOffsetBegin":226,"characterOffsetEnd":227,"pos":"JJR","before":" ","after":""},{"index":18,"word":"Joseph","originalText":"Joseph","characterOffsetBegin":227,"characterOffsetEnd":233,"pos":"NNP","before":"","after":" "},{"index":19,"word":"Chiu","originalText":"Chiu","characterOffsetBegin":234,"characterOffsetEnd":238,"pos":"NNP","before":" ","after":" "},{"index":20,"word":"-LRB-","originalText":"(","characterOffsetBegin":239,"characterOffsetEnd":240,"pos":"-LRB-","before":" ","after":""},{"index":21,"word":"josephc@cco.caltech.edu","originalText":"josephc@cco.caltech.edu","characterOffsetBegin":240,"characterOffsetEnd":263,"pos":"NN","before":"","after":""},{"index":22,"word":"-RRB-","originalText":")","characterOffsetBegin":263,"characterOffsetEnd":264,"pos":"-RRB-","before":"","after":" "},{"index":23,"word":"wrote","originalText":"wrote","characterOffsetBegin":265,"characterOffsetEnd":270,"pos":"VBD","before":" ","after":""},{"index":24,"word":":","originalText":":","characterOffsetBegin":270,"characterOffsetEnd":271,"pos":":","before":"","after":" "},{"index":25,"word":">","originalText":">","characterOffsetBegin":272,"characterOffsetEnd":273,"pos":"JJR","before":" ","after":" "},{"index":26,"word":">","originalText":">","characterOffsetBegin":274,"characterOffsetEnd":275,"pos":"JJR","before":" ","after":""},{"index":27,"word":":","originalText":":","characterOffsetBegin":275,"characterOffsetEnd":276,"pos":":","before":"","after":" "},{"index":28,"word":"Thus","originalText":"Thus","characterOffsetBegin":277,"characterOffsetEnd":281,"pos":"RB","before":" ","after":""},{"index":29,"word":",","originalText":",","characterOffsetBegin":281,"characterOffsetEnd":282,"pos":",","before":"","after":" "},{"index":30,"word":"a","originalText":"a","characterOffsetBegin":283,"characterOffsetEnd":284,"pos":"DT","before":" ","after":" "},{"index":31,"word":"deciBell","originalText":"deciBell","characterOffsetBegin":285,"characterOffsetEnd":293,"pos":"NN","before":" ","after":" "},{"index":32,"word":"-LRB-","originalText":"(","characterOffsetBegin":294,"characterOffsetEnd":295,"pos":"-LRB-","before":" ","after":""},{"index":33,"word":"deci","originalText":"deci","characterOffsetBegin":295,"characterOffsetEnd":299,"pos":"NN","before":"","after":""},{"index":34,"word":"-","originalText":"-","characterOffsetBegin":299,"characterOffsetEnd":300,"pos":":","before":"","after":""},{"index":35,"word":",","originalText":",","characterOffsetBegin":300,"characterOffsetEnd":301,"pos":",","before":"","after":" "},{"index":36,"word":"l.","originalText":"l.","characterOffsetBegin":302,"characterOffsetEnd":304,"pos":"NN","before":" ","after":""},{"index":37,"word":",","originalText":",","characterOffsetBegin":304,"characterOffsetEnd":305,"pos":",","before":"","after":" "},{"index":38,"word":"tenth","originalText":"tenth","characterOffsetBegin":306,"characterOffsetEnd":311,"pos":"NN","before":" ","after":" "},{"index":39,"word":"of","originalText":"of","characterOffsetBegin":312,"characterOffsetEnd":314,"pos":"IN","before":" ","after":" "},{"index":40,"word":"+","originalText":"+","characterOffsetBegin":315,"characterOffsetEnd":316,"pos":"CC","before":" ","after":" "},{"index":41,"word":"Bell","originalText":"Bell","characterOffsetBegin":317,"characterOffsetEnd":321,"pos":"NNP","before":" ","after":""},{"index":42,"word":"-RRB-","originalText":")","characterOffsetBegin":321,"characterOffsetEnd":322,"pos":"-RRB-","before":"","after":" "},{"index":43,"word":"is","originalText":"is","characterOffsetBegin":323,"characterOffsetEnd":325,"pos":"VBZ","before":" ","after":" "},{"index":44,"word":"a","originalText":"a","characterOffsetBegin":326,"characterOffsetEnd":327,"pos":"DT","before":" ","after":" "},{"index":45,"word":"fractional","originalText":"fractional","characterOffsetBegin":328,"characterOffsetEnd":338,"pos":"JJ","before":" ","after":" "},{"index":46,"word":"part","originalText":"part","characterOffsetBegin":339,"characterOffsetEnd":343,"pos":"NN","before":" ","after":" "},{"index":47,"word":"of","originalText":"of","characterOffsetBegin":344,"characterOffsetEnd":346,"pos":"IN","before":" ","after":" "},{"index":48,"word":"the","originalText":"the","characterOffsetBegin":347,"characterOffsetEnd":350,"pos":"DT","before":" ","after":" "},{"index":49,"word":">","originalText":">","characterOffsetBegin":351,"characterOffsetEnd":352,"pos":"JJR","before":" ","after":""},{"index":50,"word":":","originalText":":","characterOffsetBegin":352,"characterOffsetEnd":353,"pos":":","before":"","after":" "},{"index":51,"word":"original","originalText":"original","characterOffsetBegin":354,"characterOffsetEnd":362,"pos":"JJ","before":" ","after":" "},{"index":52,"word":"Bell","originalText":"Bell","characterOffsetBegin":363,"characterOffsetEnd":367,"pos":"NNP","before":" ","after":""},{"index":53,"word":".","originalText":".","characterOffsetBegin":367,"characterOffsetEnd":368,"pos":".","before":"","after":"  "}]},{"index":2,"tokens":[{"index":1,"word":"For","originalText":"For","characterOffsetBegin":370,"characterOffsetEnd":373,"pos":"IN","before":"  ","after":" "},{"index":2,"word":"example","originalText":"example","characterOffsetBegin":374,"characterOffsetEnd":381,"pos":"NN","before":" ","after":""},{"index":3,"word":",","originalText":",","characterOffsetBegin":381,"characterOffsetEnd":382,"pos":",","before":"","after":" "},{"index":4,"word":"SouthWestern","originalText":"SouthWestern","characterOffsetBegin":383,"characterOffsetEnd":395,"pos":"NNP","before":" ","after":" "},{"index":5,"word":"Bell","originalText":"Bell","characterOffsetBegin":396,"characterOffsetEnd":400,"pos":"NNP","before":" ","after":" "},{"index":6,"word":"is","originalText":"is","characterOffsetBegin":401,"characterOffsetEnd":403,"pos":"VBZ","before":" ","after":" "},{"index":7,"word":"a","originalText":"a","characterOffsetBegin":404,"characterOffsetEnd":405,"pos":"DT","before":" ","after":" "},{"index":8,"word":"deciBell","originalText":"deciBell","characterOffsetBegin":406,"characterOffsetEnd":414,"pos":"NN","before":" ","after":""},{"index":9,"word":".","originalText":".","characterOffsetBegin":414,"characterOffsetEnd":415,"pos":".","before":"","after":" "},{"index":10,"word":">","originalText":">","characterOffsetBegin":416,"characterOffsetEnd":417,"pos":"JJR","before":" ","after":" "},{"index":11,"word":">","originalText":">","characterOffsetBegin":418,"characterOffsetEnd":419,"pos":"JJR","before":" ","after":""}]},{"index":3,"tokens":[{"index":1,"word":"Out","originalText":"Out","characterOffsetBegin":419,"characterOffsetEnd":422,"pos":"IN","before":"","after":" "},{"index":2,"word":"of","originalText":"of","characterOffsetBegin":423,"characterOffsetEnd":425,"pos":"IN","before":" ","after":" "},{"index":3,"word":"what","originalText":"what","characterOffsetBegin":426,"characterOffsetEnd":430,"pos":"WP","before":" ","after":" "},{"index":4,"word":"hat","originalText":"hat","characterOffsetBegin":431,"characterOffsetEnd":434,"pos":"NN","before":" ","after":" "},{"index":5,"word":"did","originalText":"did","characterOffsetBegin":435,"characterOffsetEnd":438,"pos":"VBD","before":" ","after":" "},{"index":6,"word":"you","originalText":"you","characterOffsetBegin":439,"characterOffsetEnd":442,"pos":"PRP","before":" ","after":" "},{"index":7,"word":"pull","originalText":"pull","characterOffsetBegin":443,"characterOffsetEnd":447,"pos":"VB","before":" ","after":" "},{"index":8,"word":"this","originalText":"this","characterOffsetBegin":448,"characterOffsetEnd":452,"pos":"DT","before":" ","after":" "},{"index":9,"word":"one","originalText":"one","characterOffsetBegin":453,"characterOffsetEnd":456,"pos":"CD","before":" ","after":""},{"index":10,"word":"?","originalText":"?","characterOffsetBegin":456,"characterOffsetEnd":457,"pos":".","before":"","after":"  "}]},{"index":4,"tokens":[{"index":1,"word":"dB","originalText":"dB","characterOffsetBegin":459,"characterOffsetEnd":461,"pos":"NN","before":"  ","after":" "},{"index":2,"word":"is","originalText":"is","characterOffsetBegin":462,"characterOffsetEnd":464,"pos":"VBZ","before":" ","after":" "},{"index":3,"word":"a","originalText":"a","characterOffsetBegin":465,"characterOffsetEnd":466,"pos":"DT","before":" ","after":" "},{"index":4,"word":"ratio","originalText":"ratio","characterOffsetBegin":467,"characterOffsetEnd":472,"pos":"NN","before":" ","after":" "},{"index":5,"word":"not","originalText":"not","characterOffsetBegin":473,"characterOffsetEnd":476,"pos":"RB","before":" ","after":" "},{"index":6,"word":"an","originalText":"an","characterOffsetBegin":477,"characterOffsetEnd":479,"pos":"DT","before":" ","after":" "},{"index":7,"word":"RBOC","originalText":"RBOC","characterOffsetBegin":480,"characterOffsetEnd":484,"pos":"NN","before":" ","after":""},{"index":8,"word":"!","originalText":"!","characterOffsetBegin":484,"characterOffsetEnd":485,"pos":".","before":"","after":" "},{"index":9,"word":">","originalText":">","characterOffsetBegin":486,"characterOffsetEnd":487,"pos":"JJR","before":" ","after":" "},{"index":10,"word":">","originalText":">","characterOffsetBegin":488,"characterOffsetEnd":489,"pos":"JJR","before":" ","after":""}]},{"index":5,"tokens":[{"index":1,"word":":","originalText":":","characterOffsetBegin":489,"characterOffsetEnd":490,"pos":":","before":"","after":" "},{"index":2,"word":"And","originalText":"And","characterOffsetBegin":491,"characterOffsetEnd":494,"pos":"CC","before":" ","after":" "},{"index":3,"word":"the","originalText":"the","characterOffsetBegin":495,"characterOffsetEnd":498,"pos":"DT","before":" ","after":" "},{"index":4,"word":"measure","originalText":"measure","characterOffsetBegin":499,"characterOffsetEnd":506,"pos":"NN","before":" ","after":" "},{"index":5,"word":"of","originalText":"of","characterOffsetBegin":507,"characterOffsetEnd":509,"pos":"IN","before":" ","after":" "},{"index":6,"word":"current","originalText":"current","characterOffsetBegin":510,"characterOffsetEnd":517,"pos":"JJ","before":" ","after":""},{"index":7,"word":",","originalText":",","characterOffsetBegin":517,"characterOffsetEnd":518,"pos":",","before":"","after":" "},{"index":8,"word":"Amp","originalText":"Amp","characterOffsetBegin":519,"characterOffsetEnd":522,"pos":"NNP","before":" ","after":""},{"index":9,"word":",","originalText":",","characterOffsetBegin":522,"characterOffsetEnd":523,"pos":",","before":"","after":" "},{"index":10,"word":"is","originalText":"is","characterOffsetBegin":524,"characterOffsetEnd":526,"pos":"VBZ","before":" ","after":" "},{"index":11,"word":"actually","originalText":"actually","characterOffsetBegin":527,"characterOffsetEnd":535,"pos":"RB","before":" ","after":" "},{"index":12,"word":"named","originalText":"named","characterOffsetBegin":536,"characterOffsetEnd":541,"pos":"VBN","before":" ","after":" "},{"index":13,"word":"after","originalText":"after","characterOffsetBegin":542,"characterOffsetEnd":547,"pos":"IN","before":" ","after":" "},{"index":14,"word":"both","originalText":"both","characterOffsetBegin":548,"characterOffsetEnd":552,"pos":"CC","before":" ","after":" "},{"index":15,"word":"the","originalText":"the","characterOffsetBegin":553,"characterOffsetEnd":556,"pos":"DT","before":" ","after":" "},{"index":16,"word":"AMP","originalText":"AMP","characterOffsetBegin":557,"characterOffsetEnd":560,"pos":"NN","before":" ","after":" "},{"index":17,"word":"company","originalText":"company","characterOffsetBegin":561,"characterOffsetEnd":568,"pos":"NN","before":" ","after":" "},{"index":18,"word":">","originalText":">","characterOffsetBegin":569,"characterOffsetEnd":570,"pos":"JJR","before":" ","after":""},{"index":19,"word":":","originalText":":","characterOffsetBegin":570,"characterOffsetEnd":571,"pos":":","before":"","after":" "},{"index":20,"word":"and","originalText":"and","characterOffsetBegin":572,"characterOffsetEnd":575,"pos":"CC","before":" ","after":" "},{"index":21,"word":"the","originalText":"the","characterOffsetBegin":576,"characterOffsetEnd":579,"pos":"DT","before":" ","after":" "},{"index":22,"word":"Amphenol","originalText":"Amphenol","characterOffsetBegin":580,"characterOffsetEnd":588,"pos":"NNP","before":" ","after":" "},{"index":23,"word":"company","originalText":"company","characterOffsetBegin":589,"characterOffsetEnd":596,"pos":"NN","before":" ","after":""},{"index":24,"word":".","originalText":".","characterOffsetBegin":596,"characterOffsetEnd":597,"pos":".","before":"","after":"  "}]},{"index":6,"tokens":[{"index":1,"word":"Both","originalText":"Both","characterOffsetBegin":599,"characterOffsetEnd":603,"pos":"DT","before":"  ","after":" "},{"index":2,"word":"companies","originalText":"companies","characterOffsetBegin":604,"characterOffsetEnd":613,"pos":"NNS","before":" ","after":" "},{"index":3,"word":"revolutionized","originalText":"revolutionized","characterOffsetBegin":614,"characterOffsetEnd":628,"pos":"VBD","before":" ","after":" "},{"index":4,"word":"electronics","originalText":"electronics","characterOffsetBegin":629,"characterOffsetEnd":640,"pos":"NNS","before":" ","after":" "},{"index":5,"word":"by","originalText":"by","characterOffsetBegin":641,"characterOffsetEnd":643,"pos":"IN","before":" ","after":" "},{"index":6,"word":">","originalText":">","characterOffsetBegin":644,"characterOffsetEnd":645,"pos":"JJR","before":" ","after":""},{"index":7,"word":":","originalText":":","characterOffsetBegin":645,"characterOffsetEnd":646,"pos":":","before":"","after":" "},{"index":8,"word":"simulatenously","originalText":"simulatenously","characterOffsetBegin":647,"characterOffsetEnd":661,"pos":"NN","before":" ","after":" "},{"index":9,"word":"realizing","originalText":"realizing","characterOffsetBegin":662,"characterOffsetEnd":671,"pos":"VBG","before":" ","after":" "},{"index":10,"word":"that","originalText":"that","characterOffsetBegin":672,"characterOffsetEnd":676,"pos":"IN","before":" ","after":" "},{"index":11,"word":"the","originalText":"the","characterOffsetBegin":677,"characterOffsetEnd":680,"pos":"DT","before":" ","after":" "},{"index":12,"word":"performance","originalText":"performance","characterOffsetBegin":681,"characterOffsetEnd":692,"pos":"NN","before":" ","after":" "},{"index":13,"word":"of","originalText":"of","characterOffsetBegin":693,"characterOffsetEnd":695,"pos":"IN","before":" ","after":" "},{"index":14,"word":"connectors","originalText":"connectors","characterOffsetBegin":696,"characterOffsetEnd":706,"pos":"NNS","before":" ","after":" "},{"index":15,"word":"and","originalText":"and","characterOffsetBegin":707,"characterOffsetEnd":710,"pos":"CC","before":" ","after":" "},{"index":16,"word":"sockets","originalText":"sockets","characterOffsetBegin":711,"characterOffsetEnd":718,"pos":"NNS","before":" ","after":" "},{"index":17,"word":">","originalText":">","characterOffsetBegin":719,"characterOffsetEnd":720,"pos":"JJR","before":" ","after":""},{"index":18,"word":":","originalText":":","characterOffsetBegin":720,"characterOffsetEnd":721,"pos":":","before":"","after":" "},{"index":19,"word":"were","originalText":"were","characterOffsetBegin":722,"characterOffsetEnd":726,"pos":"VBD","before":" ","after":" "},{"index":20,"word":"affected","originalText":"affected","characterOffsetBegin":727,"characterOffsetEnd":735,"pos":"VBN","before":" ","after":" "},{"index":21,"word":"by","originalText":"by","characterOffsetBegin":736,"characterOffsetEnd":738,"pos":"IN","before":" ","after":" "},{"index":22,"word":"the","originalText":"the","characterOffsetBegin":739,"characterOffsetEnd":742,"pos":"DT","before":" ","after":" "},{"index":23,"word":"amount","originalText":"amount","characterOffsetBegin":743,"characterOffsetEnd":749,"pos":"NN","before":" ","after":" "},{"index":24,"word":"of","originalText":"of","characterOffsetBegin":750,"characterOffsetEnd":752,"pos":"IN","before":" ","after":" "},{"index":25,"word":"current","originalText":"current","characterOffsetBegin":753,"characterOffsetEnd":760,"pos":"JJ","before":" ","after":" "},{"index":26,"word":"running","originalText":"running","characterOffsetBegin":761,"characterOffsetEnd":768,"pos":"VBG","before":" ","after":" "},{"index":27,"word":"through","originalText":"through","characterOffsetBegin":769,"characterOffsetEnd":776,"pos":"IN","before":" ","after":" "},{"index":28,"word":"the","originalText":"the","characterOffsetBegin":777,"characterOffsetEnd":780,"pos":"DT","before":" ","after":" "},{"index":29,"word":"wires","originalText":"wires","characterOffsetBegin":781,"characterOffsetEnd":786,"pos":"NNS","before":" ","after":""},{"index":30,"word":".","originalText":".","characterOffsetBegin":786,"characterOffsetEnd":787,"pos":".","before":"","after":" "},{"index":31,"word":">","originalText":">","characterOffsetBegin":788,"characterOffsetEnd":789,"pos":"JJR","before":" ","after":" "},{"index":32,"word":">","originalText":">","characterOffsetBegin":790,"characterOffsetEnd":791,"pos":"JJR","before":" ","after":""}]},{"index":7,"tokens":[{"index":1,"word":"Sorry","originalText":"Sorry","characterOffsetBegin":791,"characterOffsetEnd":796,"pos":"JJ","before":"","after":""},{"index":2,"word":".","originalText":".","characterOffsetBegin":796,"characterOffsetEnd":797,"pos":".","before":"","after":"  "}]},{"index":8,"tokens":[{"index":1,"word":"The","originalText":"The","characterOffsetBegin":799,"characterOffsetEnd":802,"pos":"DT","before":"  ","after":" "},{"index":2,"word":"unit","originalText":"unit","characterOffsetBegin":803,"characterOffsetEnd":807,"pos":"NN","before":" ","after":" "},{"index":3,"word":"for","originalText":"for","characterOffsetBegin":808,"characterOffsetEnd":811,"pos":"IN","before":" ","after":" "},{"index":4,"word":"current","originalText":"current","characterOffsetBegin":812,"characterOffsetEnd":819,"pos":"JJ","before":" ","after":" "},{"index":5,"word":"is","originalText":"is","characterOffsetBegin":820,"characterOffsetEnd":822,"pos":"VBZ","before":" ","after":" "},{"index":6,"word":"the","originalText":"the","characterOffsetBegin":823,"characterOffsetEnd":826,"pos":"DT","before":" ","after":" "},{"index":7,"word":"AMPERE","originalText":"AMPERE","characterOffsetBegin":827,"characterOffsetEnd":833,"pos":"NN","before":" ","after":" "},{"index":8,"word":"which","originalText":"which","characterOffsetBegin":834,"characterOffsetEnd":839,"pos":"WDT","before":" ","after":" "},{"index":9,"word":"is","originalText":"is","characterOffsetBegin":840,"characterOffsetEnd":842,"pos":"VBZ","before":" ","after":" "},{"index":10,"word":"the","originalText":"the","characterOffsetBegin":843,"characterOffsetEnd":846,"pos":"DT","before":" ","after":" "},{"index":11,"word":"name","originalText":"name","characterOffsetBegin":847,"characterOffsetEnd":851,"pos":"NN","before":" ","after":" "},{"index":12,"word":"of","originalText":"of","characterOffsetBegin":852,"characterOffsetEnd":854,"pos":"IN","before":" ","after":" "},{"index":13,"word":"a","originalText":"a","characterOffsetBegin":855,"characterOffsetEnd":856,"pos":"DT","before":" ","after":" "},{"index":14,"word":"french-man","originalText":"french-man","characterOffsetBegin":857,"characterOffsetEnd":867,"pos":"JJ","before":" ","after":" "},{"index":15,"word":">","originalText":">","characterOffsetBegin":868,"characterOffsetEnd":869,"pos":"JJR","before":" ","after":""},{"index":16,"word":"named","originalText":"named","characterOffsetBegin":869,"characterOffsetEnd":874,"pos":"VBN","before":"","after":" "},{"index":17,"word":"AMPERE","originalText":"AMPERE","characterOffsetBegin":875,"characterOffsetEnd":881,"pos":"NNP","before":" ","after":" "},{"index":18,"word":"who","originalText":"who","characterOffsetBegin":882,"characterOffsetEnd":885,"pos":"WP","before":" ","after":" "},{"index":19,"word":"studied","originalText":"studied","characterOffsetBegin":886,"characterOffsetEnd":893,"pos":"VBD","before":" ","after":" "},{"index":20,"word":"electrical","originalText":"electrical","characterOffsetBegin":894,"characterOffsetEnd":904,"pos":"JJ","before":" ","after":" "},{"index":21,"word":"current","originalText":"current","characterOffsetBegin":905,"characterOffsetEnd":912,"pos":"JJ","before":" ","after":""},{"index":22,"word":".","originalText":".","characterOffsetBegin":912,"characterOffsetEnd":913,"pos":".","before":"","after":"  "}]},{"index":9,"tokens":[{"index":1,"word":"The","originalText":"The","characterOffsetBegin":915,"characterOffsetEnd":918,"pos":"DT","before":"  ","after":" "},{"index":2,"word":"term","originalText":"term","characterOffsetBegin":919,"characterOffsetEnd":923,"pos":"NN","before":" ","after":" "},{"index":3,"word":"AMP","originalText":"AMP","characterOffsetBegin":924,"characterOffsetEnd":927,"pos":"NN","before":" ","after":" "},{"index":4,"word":"is","originalText":"is","characterOffsetBegin":928,"characterOffsetEnd":930,"pos":"VBZ","before":" ","after":" "},{"index":5,"word":"just","originalText":"just","characterOffsetBegin":931,"characterOffsetEnd":935,"pos":"RB","before":" ","after":" "},{"index":6,"word":"an","originalText":"an","characterOffsetBegin":936,"characterOffsetEnd":938,"pos":"DT","before":" ","after":" "},{"index":7,"word":"abbreviation","originalText":"abbreviation","characterOffsetBegin":939,"characterOffsetEnd":951,"pos":"NN","before":" ","after":" "},{"index":8,"word":">","originalText":">","characterOffsetBegin":952,"characterOffsetEnd":953,"pos":"JJR","before":" ","after":""},{"index":9,"word":"of","originalText":"of","characterOffsetBegin":953,"characterOffsetEnd":955,"pos":"IN","before":"","after":" "},{"index":10,"word":"it","originalText":"it","characterOffsetBegin":956,"characterOffsetEnd":958,"pos":"PRP","before":" ","after":""},{"index":11,"word":".","originalText":".","characterOffsetBegin":958,"characterOffsetEnd":959,"pos":".","before":"","after":"  "}]},{"index":10,"tokens":[{"index":1,"word":"The","originalText":"The","characterOffsetBegin":961,"characterOffsetEnd":964,"pos":"DT","before":"  ","after":" "},{"index":2,"word":"company","originalText":"company","characterOffsetBegin":965,"characterOffsetEnd":972,"pos":"NN","before":" ","after":" "},{"index":3,"word":"AMP","originalText":"AMP","characterOffsetBegin":973,"characterOffsetEnd":976,"pos":"NN","before":" ","after":" "},{"index":4,"word":"came","originalText":"came","characterOffsetBegin":977,"characterOffsetEnd":981,"pos":"VBD","before":" ","after":" "},{"index":5,"word":"after","originalText":"after","characterOffsetBegin":982,"characterOffsetEnd":987,"pos":"IN","before":" ","after":" "},{"index":6,"word":"the","originalText":"the","characterOffsetBegin":988,"characterOffsetEnd":991,"pos":"DT","before":" ","after":" "},{"index":7,"word":"AMPERE","originalText":"AMPERE","characterOffsetBegin":992,"characterOffsetEnd":998,"pos":"NNP","before":" ","after":" "},{"index":8,"word":"unit","originalText":"unit","characterOffsetBegin":999,"characterOffsetEnd":1003,"pos":"NN","before":" ","after":" "},{"index":9,"word":"was","originalText":"was","characterOffsetBegin":1004,"characterOffsetEnd":1007,"pos":"VBD","before":" ","after":" "},{"index":10,"word":"already","originalText":"already","characterOffsetBegin":1008,"characterOffsetEnd":1015,"pos":"RB","before":" ","after":" "},{"index":11,"word":"in","originalText":"in","characterOffsetBegin":1016,"characterOffsetEnd":1018,"pos":"IN","before":" ","after":" "},{"index":12,"word":"use","originalText":"use","characterOffsetBegin":1019,"characterOffsetEnd":1022,"pos":"NN","before":" ","after":""},{"index":13,"word":".","originalText":".","characterOffsetBegin":1022,"characterOffsetEnd":1023,"pos":".","before":"","after":" "},{"index":14,"word":">","originalText":">","characterOffsetBegin":1024,"characterOffsetEnd":1025,"pos":"JJR","before":" ","after":" "},{"index":15,"word":">","originalText":">","characterOffsetBegin":1026,"characterOffsetEnd":1027,"pos":"JJR","before":" ","after":""}]},{"index":11,"tokens":[{"index":1,"word":":","originalText":":","characterOffsetBegin":1027,"characterOffsetEnd":1028,"pos":":","before":"","after":" "},{"index":2,"word":"The","originalText":"The","characterOffsetBegin":1029,"characterOffsetEnd":1032,"pos":"DT","before":" ","after":" "},{"index":3,"word":"Ohmite","originalText":"Ohmite","characterOffsetBegin":1033,"characterOffsetEnd":1039,"pos":"JJ","before":" ","after":" "},{"index":4,"word":"company","originalText":"company","characterOffsetBegin":1040,"characterOffsetEnd":1047,"pos":"NN","before":" ","after":" "},{"index":5,"word":"was","originalText":"was","characterOffsetBegin":1048,"characterOffsetEnd":1051,"pos":"VBD","before":" ","after":" "},{"index":6,"word":"the","originalText":"the","characterOffsetBegin":1052,"characterOffsetEnd":1055,"pos":"DT","before":" ","after":" "},{"index":7,"word":"first","originalText":"first","characterOffsetBegin":1056,"characterOffsetEnd":1061,"pos":"JJ","before":" ","after":" "},{"index":8,"word":"to","originalText":"to","characterOffsetBegin":1062,"characterOffsetEnd":1064,"pos":"TO","before":" ","after":" "},{"index":9,"word":"characterize","originalText":"characterize","characterOffsetBegin":1065,"characterOffsetEnd":1077,"pos":"VB","before":" ","after":" "},{"index":10,"word":"resistances","originalText":"resistances","characterOffsetBegin":1078,"characterOffsetEnd":1089,"pos":"NNS","before":" ","after":" "},{"index":11,"word":"by","originalText":"by","characterOffsetBegin":1090,"characterOffsetEnd":1092,"pos":"IN","before":" ","after":" "},{"index":12,"word":"numbers","originalText":"numbers","characterOffsetBegin":1093,"characterOffsetEnd":1100,"pos":"NNS","before":" ","after":""},{"index":13,"word":",","originalText":",","characterOffsetBegin":1100,"characterOffsetEnd":1101,"pos":",","before":"","after":" "},{"index":14,"word":">","originalText":">","characterOffsetBegin":1102,"characterOffsetEnd":1103,"pos":"JJR","before":" ","after":""},{"index":15,"word":":","originalText":":","characterOffsetBegin":1103,"characterOffsetEnd":1104,"pos":":","before":"","after":" "},{"index":16,"word":"thus","originalText":"thus","characterOffsetBegin":1105,"characterOffsetEnd":1109,"pos":"RB","before":" ","after":" "},{"index":17,"word":"our","originalText":"our","characterOffsetBegin":1110,"characterOffsetEnd":1113,"pos":"PRP$","before":" ","after":" "},{"index":18,"word":"use","originalText":"use","characterOffsetBegin":1114,"characterOffsetEnd":1117,"pos":"NN","before":" ","after":" "},{"index":19,"word":"of","originalText":"of","characterOffsetBegin":1118,"characterOffsetEnd":1120,"pos":"IN","before":" ","after":" "},{"index":20,"word":"the","originalText":"the","characterOffsetBegin":1121,"characterOffsetEnd":1124,"pos":"DT","before":" ","after":" "},{"index":21,"word":"Ohms","originalText":"Ohms","characterOffsetBegin":1125,"characterOffsetEnd":1129,"pos":"NNP","before":" ","after":""},{"index":22,"word":"...","originalText":"...","characterOffsetBegin":1129,"characterOffsetEnd":1132,"pos":":","before":"","after":" "},{"index":23,"word":">","originalText":">","characterOffsetBegin":1133,"characterOffsetEnd":1134,"pos":"JJR","before":" ","after":" "},{"index":24,"word":">","originalText":">","characterOffsetBegin":1135,"characterOffsetEnd":1136,"pos":"JJR","before":" ","after":""},{"index":25,"word":"I","originalText":"I","characterOffsetBegin":1136,"characterOffsetEnd":1137,"pos":"PRP","before":"","after":" "},{"index":26,"word":"do","originalText":"do","characterOffsetBegin":1138,"characterOffsetEnd":1140,"pos":"VBP","before":" ","after":""},{"index":27,"word":"n't","originalText":"n't","characterOffsetBegin":1140,"characterOffsetEnd":1143,"pos":"RB","before":"","after":" "},{"index":28,"word":"know","originalText":"know","characterOffsetBegin":1144,"characterOffsetEnd":1148,"pos":"VB","before":" ","after":" "},{"index":29,"word":"about","originalText":"about","characterOffsetBegin":1149,"characterOffsetEnd":1154,"pos":"IN","before":" ","after":" "},{"index":30,"word":"this","originalText":"this","characterOffsetBegin":1155,"characterOffsetEnd":1159,"pos":"DT","before":" ","after":" "},{"index":31,"word":"one","originalText":"one","characterOffsetBegin":1160,"characterOffsetEnd":1163,"pos":"CD","before":" ","after":""},{"index":32,"word":",","originalText":",","characterOffsetBegin":1163,"characterOffsetEnd":1164,"pos":",","before":"","after":" "},{"index":33,"word":"but","originalText":"but","characterOffsetBegin":1165,"characterOffsetEnd":1168,"pos":"CC","before":" ","after":" "},{"index":34,"word":"it","originalText":"it","characterOffsetBegin":1169,"characterOffsetEnd":1171,"pos":"PRP","before":" ","after":" "},{"index":35,"word":"does","originalText":"does","characterOffsetBegin":1172,"characterOffsetEnd":1176,"pos":"VBZ","before":" ","after":""},{"index":36,"word":"n't","originalText":"n't","characterOffsetBegin":1176,"characterOffsetEnd":1179,"pos":"RB","before":"","after":" "},{"index":37,"word":"sound","originalText":"sound","characterOffsetBegin":1180,"characterOffsetEnd":1185,"pos":"VB","before":" ","after":" "},{"index":38,"word":"right","originalText":"right","characterOffsetBegin":1186,"characterOffsetEnd":1191,"pos":"NN","before":" ","after":""},{"index":39,"word":".","originalText":".","characterOffsetBegin":1191,"characterOffsetEnd":1192,"pos":".","before":"","after":" "},{"index":40,"word":">","originalText":">","characterOffsetBegin":1193,"characterOffsetEnd":1194,"pos":"JJR","before":" ","after":" "},{"index":41,"word":">","originalText":">","characterOffsetBegin":1195,"characterOffsetEnd":1196,"pos":"JJR","before":" ","after":""}]},{"index":12,"tokens":[{"index":1,"word":":","originalText":":","characterOffsetBegin":1196,"characterOffsetEnd":1197,"pos":":","before":"","after":" "},{"index":2,"word":">","originalText":">","characterOffsetBegin":1198,"characterOffsetEnd":1199,"pos":"JJR","before":" ","after":""},{"index":3,"word":":","originalText":":","characterOffsetBegin":1199,"characterOffsetEnd":1200,"pos":":","before":"","after":" "},{"index":4,"word":"Alexander","originalText":"Alexander","characterOffsetBegin":1201,"characterOffsetEnd":1210,"pos":"NNP","before":" ","after":" "},{"index":5,"word":"Graham","originalText":"Graham","characterOffsetBegin":1211,"characterOffsetEnd":1217,"pos":"NNP","before":" ","after":" "},{"index":6,"word":"Bell","originalText":"Bell","characterOffsetBegin":1218,"characterOffsetEnd":1222,"pos":"NNP","before":" ","after":""},{"index":7,"word":",","originalText":",","characterOffsetBegin":1222,"characterOffsetEnd":1223,"pos":",","before":"","after":" "},{"index":8,"word":"actually","originalText":"actually","characterOffsetBegin":1224,"characterOffsetEnd":1232,"pos":"RB","before":" ","after":""},{"index":9,"word":",","originalText":",","characterOffsetBegin":1232,"characterOffsetEnd":1233,"pos":",","before":"","after":" "},{"index":10,"word":"is","originalText":"is","characterOffsetBegin":1234,"characterOffsetEnd":1236,"pos":"VBZ","before":" ","after":" "},{"index":11,"word":"where","originalText":"where","characterOffsetBegin":1237,"characterOffsetEnd":1242,"pos":"WRB","before":" ","after":" "},{"index":12,"word":"Bell","originalText":"Bell","characterOffsetBegin":1243,"characterOffsetEnd":1247,"pos":"NNP","before":" ","after":" "},{"index":13,"word":"came","originalText":"came","characterOffsetBegin":1248,"characterOffsetEnd":1252,"pos":"VBD","before":" ","after":" "},{"index":14,"word":"from","originalText":"from","characterOffsetBegin":1253,"characterOffsetEnd":1257,"pos":"IN","before":" ","after":""},{"index":15,"word":"...","originalText":"...","characterOffsetBegin":1257,"characterOffsetEnd":1260,"pos":":","before":"","after":" "},{"index":16,"word":">","originalText":">","characterOffsetBegin":1261,"characterOffsetEnd":1262,"pos":"JJR","before":" ","after":""},{"index":17,"word":"Well","originalText":"Well","characterOffsetBegin":1262,"characterOffsetEnd":1266,"pos":"UH","before":"","after":" "},{"index":18,"word":"you","originalText":"you","characterOffsetBegin":1267,"characterOffsetEnd":1270,"pos":"PRP","before":" ","after":" "},{"index":19,"word":"got","originalText":"got","characterOffsetBegin":1271,"characterOffsetEnd":1274,"pos":"VBD","before":" ","after":" "},{"index":20,"word":"one","originalText":"one","characterOffsetBegin":1275,"characterOffsetEnd":1278,"pos":"CD","before":" ","after":" "},{"index":21,"word":"thing","originalText":"thing","characterOffsetBegin":1279,"characterOffsetEnd":1284,"pos":"NN","before":" ","after":" "},{"index":22,"word":"right","originalText":"right","characterOffsetBegin":1285,"characterOffsetEnd":1290,"pos":"RB","before":" ","after":""},{"index":23,"word":"!","originalText":"!","characterOffsetBegin":1290,"characterOffsetEnd":1291,"pos":".","before":"","after":" "},{"index":24,"word":">","originalText":">","characterOffsetBegin":1292,"characterOffsetEnd":1293,"pos":"JJR","before":" ","after":""}]},{"index":13,"tokens":[{"index":1,"word":":","originalText":":","characterOffsetBegin":1293,"characterOffsetEnd":1294,"pos":":","before":"","after":""},{"index":2,"word":"Actually","originalText":"Actually","characterOffsetBegin":1294,"characterOffsetEnd":1302,"pos":"RB","before":"","after":""},{"index":3,"word":",","originalText":",","characterOffsetBegin":1302,"characterOffsetEnd":1303,"pos":",","before":"","after":" "},{"index":4,"word":"I","originalText":"I","characterOffsetBegin":1304,"characterOffsetEnd":1305,"pos":"PRP","before":" ","after":" "},{"index":5,"word":"think","originalText":"think","characterOffsetBegin":1306,"characterOffsetEnd":1311,"pos":"VBP","before":" ","after":" "},{"index":6,"word":"J.","originalText":"J.","characterOffsetBegin":1312,"characterOffsetEnd":1314,"pos":"NNP","before":" ","after":" "},{"index":7,"word":"Chiu","originalText":"Chiu","characterOffsetBegin":1315,"characterOffsetEnd":1319,"pos":"NNP","before":" ","after":" "},{"index":8,"word":"knows","originalText":"knows","characterOffsetBegin":1320,"characterOffsetEnd":1325,"pos":"VBZ","before":" ","after":" "},{"index":9,"word":"the","originalText":"the","characterOffsetBegin":1326,"characterOffsetEnd":1329,"pos":"DT","before":" ","after":" "},{"index":10,"word":"score","originalText":"score","characterOffsetBegin":1330,"characterOffsetEnd":1335,"pos":"NN","before":" ","after":" "},{"index":11,"word":"and","originalText":"and","characterOffsetBegin":1336,"characterOffsetEnd":1339,"pos":"CC","before":" ","after":" "},{"index":12,"word":"is","originalText":"is","characterOffsetBegin":1340,"characterOffsetEnd":1342,"pos":"VBZ","before":" ","after":" "},{"index":13,"word":"just","originalText":"just","characterOffsetBegin":1343,"characterOffsetEnd":1347,"pos":"RB","before":" ","after":" "},{"index":14,"word":"beingsilly","originalText":"beingsilly","characterOffsetBegin":1348,"characterOffsetEnd":1358,"pos":"RB","before":" ","after":""},{"index":15,"word":".","originalText":".","characterOffsetBegin":1358,"characterOffsetEnd":1359,"pos":".","before":"","after":" "}]},{"index":14,"tokens":[{"index":1,"word":"However","originalText":"However","characterOffsetBegin":1360,"characterOffsetEnd":1367,"pos":"RB","before":" ","after":""},{"index":2,"word":",","originalText":",","characterOffsetBegin":1367,"characterOffsetEnd":1368,"pos":",","before":"","after":" "},{"index":3,"word":"``","originalText":"\"","characterOffsetBegin":1369,"characterOffsetEnd":1370,"pos":"``","before":" ","after":""},{"index":4,"word":"decibel","originalText":"decibel","characterOffsetBegin":1370,"characterOffsetEnd":1377,"pos":"NN","before":"","after":""},{"index":5,"word":"''","originalText":"\"","characterOffsetBegin":1377,"characterOffsetEnd":1378,"pos":"''","before":"","after":" "},{"index":6,"word":"is","originalText":"is","characterOffsetBegin":1379,"characterOffsetEnd":1381,"pos":"VBZ","before":" ","after":" "},{"index":7,"word":"in","originalText":"in","characterOffsetBegin":1382,"characterOffsetEnd":1384,"pos":"IN","before":" ","after":" "},{"index":8,"word":"fact","originalText":"fact","characterOffsetBegin":1385,"characterOffsetEnd":1389,"pos":"NN","before":" ","after":" "},{"index":9,"word":"1/10th","originalText":"1/10th","characterOffsetBegin":1390,"characterOffsetEnd":1396,"pos":"NN","before":" ","after":" "},{"index":10,"word":"of","originalText":"of","characterOffsetBegin":1397,"characterOffsetEnd":1399,"pos":"IN","before":" ","after":" "},{"index":11,"word":"a","originalText":"a","characterOffsetBegin":1400,"characterOffsetEnd":1401,"pos":"DT","before":" ","after":" "},{"index":12,"word":"bel","originalText":"bel","characterOffsetBegin":1402,"characterOffsetEnd":1405,"pos":"NN","before":" ","after":""},{"index":13,"word":".","originalText":".","characterOffsetBegin":1405,"characterOffsetEnd":1406,"pos":".","before":"","after":" "}]},{"index":15,"tokens":[{"index":1,"word":"He","originalText":"He","characterOffsetBegin":1407,"characterOffsetEnd":1409,"pos":"PRP","before":" ","after":" "},{"index":2,"word":"isright","originalText":"isright","characterOffsetBegin":1410,"characterOffsetEnd":1417,"pos":"VBZ","before":" ","after":" "},{"index":3,"word":"on","originalText":"on","characterOffsetBegin":1418,"characterOffsetEnd":1420,"pos":"IN","before":" ","after":" "},{"index":4,"word":"that","originalText":"that","characterOffsetBegin":1421,"characterOffsetEnd":1425,"pos":"DT","before":" ","after":" "},{"index":5,"word":"one","originalText":"one","characterOffsetBegin":1426,"characterOffsetEnd":1429,"pos":"CD","before":" ","after":""},{"index":6,"word":",","originalText":",","characterOffsetBegin":1429,"characterOffsetEnd":1430,"pos":",","before":"","after":" "},{"index":7,"word":"but","originalText":"but","characterOffsetBegin":1431,"characterOffsetEnd":1434,"pos":"CC","before":" ","after":" "},{"index":8,"word":"I","originalText":"I","characterOffsetBegin":1435,"characterOffsetEnd":1436,"pos":"PRP","before":" ","after":" "},{"index":9,"word":"do","originalText":"do","characterOffsetBegin":1437,"characterOffsetEnd":1439,"pos":"VBP","before":" ","after":""},{"index":10,"word":"n't","originalText":"n't","characterOffsetBegin":1439,"characterOffsetEnd":1442,"pos":"RB","before":"","after":" "},{"index":11,"word":"know","originalText":"know","characterOffsetBegin":1443,"characterOffsetEnd":1447,"pos":"VB","before":" ","after":" "},{"index":12,"word":"if","originalText":"if","characterOffsetBegin":1448,"characterOffsetEnd":1450,"pos":"IN","before":" ","after":" "},{"index":13,"word":"it","originalText":"it","characterOffsetBegin":1451,"characterOffsetEnd":1453,"pos":"PRP","before":" ","after":" "},{"index":14,"word":"was","originalText":"was","characterOffsetBegin":1454,"characterOffsetEnd":1457,"pos":"VBD","before":" ","after":" "},{"index":15,"word":"accidental","originalText":"accidental","characterOffsetBegin":1458,"characterOffsetEnd":1468,"pos":"JJ","before":" ","after":" "},{"index":16,"word":"or","originalText":"or","characterOffsetBegin":1469,"characterOffsetEnd":1471,"pos":"CC","before":" ","after":" "},{"index":17,"word":"not.Strictly","originalText":"not.Strictly","characterOffsetBegin":1472,"characterOffsetEnd":1484,"pos":"RB","before":" ","after":" "},{"index":18,"word":"defined","originalText":"defined","characterOffsetBegin":1485,"characterOffsetEnd":1492,"pos":"VBN","before":" ","after":""},{"index":19,"word":",","originalText":",","characterOffsetBegin":1492,"characterOffsetEnd":1493,"pos":",","before":"","after":" "},{"index":20,"word":"a","originalText":"a","characterOffsetBegin":1494,"characterOffsetEnd":1495,"pos":"DT","before":" ","after":" "},{"index":21,"word":"bel","originalText":"bel","characterOffsetBegin":1496,"characterOffsetEnd":1499,"pos":"NN","before":" ","after":" "},{"index":22,"word":"is","originalText":"is","characterOffsetBegin":1500,"characterOffsetEnd":1502,"pos":"VBZ","before":" ","after":" "},{"index":23,"word":"the","originalText":"the","characterOffsetBegin":1503,"characterOffsetEnd":1506,"pos":"DT","before":" ","after":" "},{"index":24,"word":"ratio","originalText":"ratio","characterOffsetBegin":1507,"characterOffsetEnd":1512,"pos":"NN","before":" ","after":" "},{"index":25,"word":"of","originalText":"of","characterOffsetBegin":1513,"characterOffsetEnd":1515,"pos":"IN","before":" ","after":" "},{"index":26,"word":"the","originalText":"the","characterOffsetBegin":1516,"characterOffsetEnd":1519,"pos":"DT","before":" ","after":" "},{"index":27,"word":"log","originalText":"log","characterOffsetBegin":1520,"characterOffsetEnd":1523,"pos":"NN","before":" ","after":" "},{"index":28,"word":"of","originalText":"of","characterOffsetBegin":1524,"characterOffsetEnd":1526,"pos":"IN","before":" ","after":" "},{"index":29,"word":"two","originalText":"two","characterOffsetBegin":1527,"characterOffsetEnd":1530,"pos":"CD","before":" ","after":" "},{"index":30,"word":"power","originalText":"power","characterOffsetBegin":1531,"characterOffsetEnd":1536,"pos":"NN","before":" ","after":" "},{"index":31,"word":"levels","originalText":"levels","characterOffsetBegin":1537,"characterOffsetEnd":1543,"pos":"NNS","before":" ","after":""},{"index":32,"word":",","originalText":",","characterOffsetBegin":1543,"characterOffsetEnd":1544,"pos":",","before":"","after":""},{"index":33,"word":"and","originalText":"and","characterOffsetBegin":1544,"characterOffsetEnd":1547,"pos":"CC","before":"","after":" "},{"index":34,"word":"a","originalText":"a","characterOffsetBegin":1548,"characterOffsetEnd":1549,"pos":"DT","before":" ","after":" "},{"index":35,"word":"decibel","originalText":"decibel","characterOffsetBegin":1550,"characterOffsetEnd":1557,"pos":"NN","before":" ","after":" "},{"index":36,"word":"is","originalText":"is","characterOffsetBegin":1558,"characterOffsetEnd":1560,"pos":"VBZ","before":" ","after":" "},{"index":37,"word":"1/10th","originalText":"1/10th","characterOffsetBegin":1561,"characterOffsetEnd":1567,"pos":"NN","before":" ","after":" "},{"index":38,"word":"of","originalText":"of","characterOffsetBegin":1568,"characterOffsetEnd":1570,"pos":"IN","before":" ","after":" "},{"index":39,"word":"a","originalText":"a","characterOffsetBegin":1571,"characterOffsetEnd":1572,"pos":"DT","before":" ","after":" "},{"index":40,"word":"bel","originalText":"bel","characterOffsetBegin":1573,"characterOffsetEnd":1576,"pos":"NN","before":" ","after":" "},{"index":41,"word":"so","originalText":"so","characterOffsetBegin":1577,"characterOffsetEnd":1579,"pos":"IN","before":" ","after":" "},{"index":42,"word":"you","originalText":"you","characterOffsetBegin":1580,"characterOffsetEnd":1583,"pos":"PRP","before":" ","after":" "},{"index":43,"word":"have","originalText":"have","characterOffsetBegin":1584,"characterOffsetEnd":1588,"pos":"VBP","before":" ","after":" "},{"index":44,"word":"10X","originalText":"10X","characterOffsetBegin":1589,"characterOffsetEnd":1592,"pos":"NN","before":" ","after":" "},{"index":45,"word":"decibels","originalText":"decibels","characterOffsetBegin":1593,"characterOffsetEnd":1601,"pos":"NNS","before":" ","after":" "},{"index":46,"word":"for","originalText":"for","characterOffsetBegin":1602,"characterOffsetEnd":1605,"pos":"IN","before":" ","after":" "},{"index":47,"word":"every","originalText":"every","characterOffsetBegin":1606,"characterOffsetEnd":1611,"pos":"DT","before":" ","after":" "},{"index":48,"word":"bel","originalText":"bel","characterOffsetBegin":1612,"characterOffsetEnd":1615,"pos":"NN","before":" ","after":""},{"index":49,"word":",","originalText":",","characterOffsetBegin":1615,"characterOffsetEnd":1616,"pos":",","before":"","after":""},{"index":50,"word":"hence","originalText":"hence","characterOffsetBegin":1616,"characterOffsetEnd":1621,"pos":"RB","before":"","after":" "},{"index":51,"word":"bel","originalText":"bel","characterOffsetBegin":1622,"characterOffsetEnd":1625,"pos":"NN","before":" ","after":""},{"index":52,"word":"=","originalText":"=","characterOffsetBegin":1625,"characterOffsetEnd":1626,"pos":"JJ","before":"","after":""},{"index":53,"word":"log","originalText":"log","characterOffsetBegin":1626,"characterOffsetEnd":1629,"pos":"NN","before":"","after":""},{"index":54,"word":"-LRB-","originalText":"(","characterOffsetBegin":1629,"characterOffsetEnd":1630,"pos":"-LRB-","before":"","after":""},{"index":55,"word":"P2/P1","originalText":"P2/P1","characterOffsetBegin":1630,"characterOffsetEnd":1635,"pos":"NN","before":"","after":""},{"index":56,"word":"-RRB-","originalText":")","characterOffsetBegin":1635,"characterOffsetEnd":1636,"pos":"-RRB-","before":"","after":" "},{"index":57,"word":"and","originalText":"and","characterOffsetBegin":1637,"characterOffsetEnd":1640,"pos":"CC","before":" ","after":" "},{"index":58,"word":"decibel","originalText":"decibel","characterOffsetBegin":1641,"characterOffsetEnd":1648,"pos":"NN","before":" ","after":""},{"index":59,"word":"=","originalText":"=","characterOffsetBegin":1648,"characterOffsetEnd":1649,"pos":"JJ","before":"","after":""},{"index":60,"word":"10Xlog","originalText":"10Xlog","characterOffsetBegin":1649,"characterOffsetEnd":1655,"pos":"NN","before":"","after":""},{"index":61,"word":"-LRB-","originalText":"(","characterOffsetBegin":1655,"characterOffsetEnd":1656,"pos":"-LRB-","before":"","after":""},{"index":62,"word":"P2/P1","originalText":"P2/P1","characterOffsetBegin":1656,"characterOffsetEnd":1661,"pos":"NN","before":"","after":""},{"index":63,"word":"-RRB-","originalText":")","characterOffsetBegin":1661,"characterOffsetEnd":1662,"pos":"-RRB-","before":"","after":""},{"index":64,"word":".","originalText":".","characterOffsetBegin":1662,"characterOffsetEnd":1663,"pos":".","before":"","after":""}]},{"index":16,"tokens":[{"index":1,"word":"The","originalText":"The","characterOffsetBegin":1663,"characterOffsetEnd":1666,"pos":"DT","before":"","after":" "},{"index":2,"word":"bel","originalText":"bel","characterOffsetBegin":1667,"characterOffsetEnd":1670,"pos":"NN","before":" ","after":""},{"index":3,"word":",","originalText":",","characterOffsetBegin":1670,"characterOffsetEnd":1671,"pos":",","before":"","after":" "},{"index":4,"word":"ohm","originalText":"ohm","characterOffsetBegin":1672,"characterOffsetEnd":1675,"pos":"NN","before":" ","after":""},{"index":5,"word":",","originalText":",","characterOffsetBegin":1675,"characterOffsetEnd":1676,"pos":",","before":"","after":" "},{"index":6,"word":"volt","originalText":"volt","characterOffsetBegin":1677,"characterOffsetEnd":1681,"pos":"NN","before":" ","after":""},{"index":7,"word":",","originalText":",","characterOffsetBegin":1681,"characterOffsetEnd":1682,"pos":",","before":"","after":" "},{"index":8,"word":"farad","originalText":"farad","characterOffsetBegin":1683,"characterOffsetEnd":1688,"pos":"NN","before":" ","after":""},{"index":9,"word":",","originalText":",","characterOffsetBegin":1688,"characterOffsetEnd":1689,"pos":",","before":"","after":" "},{"index":10,"word":"ampere","originalText":"ampere","characterOffsetBegin":1690,"characterOffsetEnd":1696,"pos":"NN","before":" ","after":""},{"index":11,"word":",","originalText":",","characterOffsetBegin":1696,"characterOffsetEnd":1697,"pos":",","before":"","after":" "},{"index":12,"word":"watt","originalText":"watt","characterOffsetBegin":1698,"characterOffsetEnd":1702,"pos":"NN","before":" ","after":""},{"index":13,"word":",","originalText":",","characterOffsetBegin":1702,"characterOffsetEnd":1703,"pos":",","before":"","after":" "},{"index":14,"word":"hertz","originalText":"hertz","characterOffsetBegin":1704,"characterOffsetEnd":1709,"pos":"NN","before":" ","after":""},{"index":15,"word":",","originalText":",","characterOffsetBegin":1709,"characterOffsetEnd":1710,"pos":",","before":"","after":" "},{"index":16,"word":"henry","originalText":"henry","characterOffsetBegin":1711,"characterOffsetEnd":1716,"pos":"NN","before":" ","after":""},{"index":17,"word":",","originalText":",","characterOffsetBegin":1716,"characterOffsetEnd":1717,"pos":",","before":"","after":" "},{"index":18,"word":"etc.","originalText":"etc.","characterOffsetBegin":1718,"characterOffsetEnd":1722,"pos":"FW","before":" ","after":" "},{"index":19,"word":"areall","originalText":"areall","characterOffsetBegin":1723,"characterOffsetEnd":1729,"pos":"FW","before":" ","after":" "},{"index":20,"word":"named","originalText":"named","characterOffsetBegin":1730,"characterOffsetEnd":1735,"pos":"VBN","before":" ","after":" "},{"index":21,"word":"for","originalText":"for","characterOffsetBegin":1736,"characterOffsetEnd":1739,"pos":"IN","before":" ","after":" "},{"index":22,"word":"pioneers","originalText":"pioneers","characterOffsetBegin":1740,"characterOffsetEnd":1748,"pos":"NNS","before":" ","after":" "},{"index":23,"word":"in","originalText":"in","characterOffsetBegin":1749,"characterOffsetEnd":1751,"pos":"IN","before":" ","after":" "},{"index":24,"word":"the","originalText":"the","characterOffsetBegin":1752,"characterOffsetEnd":1755,"pos":"DT","before":" ","after":" "},{"index":25,"word":"field","originalText":"field","characterOffsetBegin":1756,"characterOffsetEnd":1761,"pos":"NN","before":" ","after":""},{"index":26,"word":".","originalText":".","characterOffsetBegin":1761,"characterOffsetEnd":1762,"pos":".","before":"","after":" "}]},{"index":17,"tokens":[{"index":1,"word":"It","originalText":"It","characterOffsetBegin":1763,"characterOffsetEnd":1765,"pos":"PRP","before":" ","after":""},{"index":2,"word":"'s","originalText":"'s","characterOffsetBegin":1765,"characterOffsetEnd":1767,"pos":"VBZ","before":"","after":" "},{"index":3,"word":"a","originalText":"a","characterOffsetBegin":1768,"characterOffsetEnd":1769,"pos":"DT","before":" ","after":" "},{"index":4,"word":"traditional","originalText":"traditional","characterOffsetBegin":1770,"characterOffsetEnd":1781,"pos":"JJ","before":" ","after":" "},{"index":5,"word":"and","originalText":"and","characterOffsetBegin":1782,"characterOffsetEnd":1785,"pos":"CC","before":" ","after":" "},{"index":6,"word":"fineway","originalText":"fineway","characterOffsetBegin":1786,"characterOffsetEnd":1793,"pos":"NN","before":" ","after":" "},{"index":7,"word":"to","originalText":"to","characterOffsetBegin":1794,"characterOffsetEnd":1796,"pos":"TO","before":" ","after":" "},{"index":8,"word":"honor","originalText":"honor","characterOffsetBegin":1797,"characterOffsetEnd":1802,"pos":"VB","before":" ","after":" "},{"index":9,"word":"researchers","originalText":"researchers","characterOffsetBegin":1803,"characterOffsetEnd":1814,"pos":"NNS","before":" ","after":" "},{"index":10,"word":"who","originalText":"who","characterOffsetBegin":1815,"characterOffsetEnd":1818,"pos":"WP","before":" ","after":" "},{"index":11,"word":"discover","originalText":"discover","characterOffsetBegin":1819,"characterOffsetEnd":1827,"pos":"VBP","before":" ","after":" "},{"index":12,"word":"new","originalText":"new","characterOffsetBegin":1828,"characterOffsetEnd":1831,"pos":"JJ","before":" ","after":" "},{"index":13,"word":"knowledge","originalText":"knowledge","characterOffsetBegin":1832,"characterOffsetEnd":1841,"pos":"NN","before":" ","after":" "},{"index":14,"word":"in","originalText":"in","characterOffsetBegin":1842,"characterOffsetEnd":1844,"pos":"IN","before":" ","after":" "},{"index":15,"word":"a","originalText":"a","characterOffsetBegin":1845,"characterOffsetEnd":1846,"pos":"DT","before":" ","after":" "},{"index":16,"word":"new","originalText":"new","characterOffsetBegin":1847,"characterOffsetEnd":1850,"pos":"JJ","before":" ","after":" "},{"index":17,"word":"field.Hertz","originalText":"field.Hertz","characterOffsetBegin":1851,"characterOffsetEnd":1862,"pos":"NN","before":" ","after":" "},{"index":18,"word":"was","originalText":"was","characterOffsetBegin":1863,"characterOffsetEnd":1866,"pos":"VBD","before":" ","after":" "},{"index":19,"word":"one","originalText":"one","characterOffsetBegin":1867,"characterOffsetEnd":1870,"pos":"CD","before":" ","after":" "},{"index":20,"word":"of","originalText":"of","characterOffsetBegin":1871,"characterOffsetEnd":1873,"pos":"IN","before":" ","after":" "},{"index":21,"word":"the","originalText":"the","characterOffsetBegin":1874,"characterOffsetEnd":1877,"pos":"DT","before":" ","after":" "},{"index":22,"word":"most","originalText":"most","characterOffsetBegin":1878,"characterOffsetEnd":1882,"pos":"RBS","before":" ","after":" "},{"index":23,"word":"important","originalText":"important","characterOffsetBegin":1883,"characterOffsetEnd":1892,"pos":"JJ","before":" ","after":" "},{"index":24,"word":"of","originalText":"of","characterOffsetBegin":1893,"characterOffsetEnd":1895,"pos":"IN","before":" ","after":" "},{"index":25,"word":"the","originalText":"the","characterOffsetBegin":1896,"characterOffsetEnd":1899,"pos":"DT","before":" ","after":" "},{"index":26,"word":"early","originalText":"early","characterOffsetBegin":1900,"characterOffsetEnd":1905,"pos":"JJ","before":" ","after":" "},{"index":27,"word":"electronics","originalText":"electronics","characterOffsetBegin":1906,"characterOffsetEnd":1917,"pos":"NNS","before":" ","after":" "},{"index":28,"word":"explorers","originalText":"explorers","characterOffsetBegin":1918,"characterOffsetEnd":1927,"pos":"NNS","before":" ","after":""},{"index":29,"word":",","originalText":",","characterOffsetBegin":1927,"characterOffsetEnd":1928,"pos":",","before":"","after":""},{"index":30,"word":"but","originalText":"but","characterOffsetBegin":1928,"characterOffsetEnd":1931,"pos":"CC","before":"","after":" "},{"index":31,"word":"had","originalText":"had","characterOffsetBegin":1932,"characterOffsetEnd":1935,"pos":"VBD","before":" ","after":" "},{"index":32,"word":"been","originalText":"been","characterOffsetBegin":1936,"characterOffsetEnd":1940,"pos":"VBN","before":" ","after":" "},{"index":33,"word":"left","originalText":"left","characterOffsetBegin":1941,"characterOffsetEnd":1945,"pos":"VBN","before":" ","after":" "},{"index":34,"word":"out","originalText":"out","characterOffsetBegin":1946,"characterOffsetEnd":1949,"pos":"RP","before":" ","after":" "},{"index":35,"word":"in","originalText":"in","characterOffsetBegin":1950,"characterOffsetEnd":1952,"pos":"IN","before":" ","after":" "},{"index":36,"word":"having","originalText":"having","characterOffsetBegin":1953,"characterOffsetEnd":1959,"pos":"VBG","before":" ","after":" "},{"index":37,"word":"a","originalText":"a","characterOffsetBegin":1960,"characterOffsetEnd":1961,"pos":"DT","before":" ","after":" "},{"index":38,"word":"term","originalText":"term","characterOffsetBegin":1962,"characterOffsetEnd":1966,"pos":"NN","before":" ","after":" "},{"index":39,"word":"or","originalText":"or","characterOffsetBegin":1967,"characterOffsetEnd":1969,"pos":"CC","before":" ","after":" "},{"index":40,"word":"unit","originalText":"unit","characterOffsetBegin":1970,"characterOffsetEnd":1974,"pos":"NN","before":" ","after":" "},{"index":41,"word":"named","originalText":"named","characterOffsetBegin":1975,"characterOffsetEnd":1980,"pos":"VBN","before":" ","after":" "},{"index":42,"word":"after","originalText":"after","characterOffsetBegin":1981,"characterOffsetEnd":1986,"pos":"IN","before":" ","after":" "},{"index":43,"word":"himuntil","originalText":"himuntil","characterOffsetBegin":1987,"characterOffsetEnd":1995,"pos":"NN","before":" ","after":" "},{"index":44,"word":"recently","originalText":"recently","characterOffsetBegin":1996,"characterOffsetEnd":2004,"pos":"RB","before":" ","after":""},{"index":45,"word":",","originalText":",","characterOffsetBegin":2004,"characterOffsetEnd":2005,"pos":",","before":"","after":" "},{"index":46,"word":"-LRB-","originalText":"(","characterOffsetBegin":2006,"characterOffsetEnd":2007,"pos":"-LRB-","before":" ","after":""},{"index":47,"word":"1960","originalText":"1960","characterOffsetBegin":2007,"characterOffsetEnd":2011,"pos":"CD","before":"","after":""},{"index":48,"word":"'s","originalText":"'s","characterOffsetBegin":2011,"characterOffsetEnd":2013,"pos":"POS","before":"","after":""},{"index":49,"word":",","originalText":",","characterOffsetBegin":2013,"characterOffsetEnd":2014,"pos":",","before":"","after":" "},{"index":50,"word":"prior","originalText":"prior","characterOffsetBegin":2015,"characterOffsetEnd":2020,"pos":"RB","before":" ","after":" "},{"index":51,"word":"to","originalText":"to","characterOffsetBegin":2021,"characterOffsetEnd":2023,"pos":"TO","before":" ","after":" "},{"index":52,"word":"that","originalText":"that","characterOffsetBegin":2024,"characterOffsetEnd":2028,"pos":"DT","before":" ","after":" "},{"index":53,"word":"what","originalText":"what","characterOffsetBegin":2029,"characterOffsetEnd":2033,"pos":"WP","before":" ","after":" "},{"index":54,"word":"is","originalText":"is","characterOffsetBegin":2034,"characterOffsetEnd":2036,"pos":"VBZ","before":" ","after":" "},{"index":55,"word":"now","originalText":"now","characterOffsetBegin":2037,"characterOffsetEnd":2040,"pos":"RB","before":" ","after":" "},{"index":56,"word":"a","originalText":"a","characterOffsetBegin":2041,"characterOffsetEnd":2042,"pos":"DT","before":" ","after":" "},{"index":57,"word":"hertz","originalText":"hertz","characterOffsetBegin":2043,"characterOffsetEnd":2048,"pos":"NN","before":" ","after":" "},{"index":58,"word":"was","originalText":"was","characterOffsetBegin":2049,"characterOffsetEnd":2052,"pos":"VBD","before":" ","after":" "},{"index":59,"word":"a","originalText":"a","characterOffsetBegin":2053,"characterOffsetEnd":2054,"pos":"DT","before":" ","after":" "},{"index":60,"word":"cps","originalText":"cps","characterOffsetBegin":2055,"characterOffsetEnd":2058,"pos":"NNS","before":" ","after":""},{"index":61,"word":".","originalText":".","characterOffsetBegin":2058,"characterOffsetEnd":2059,"pos":".","before":"","after":""},{"index":62,"word":"-RRB-","originalText":")","characterOffsetBegin":2059,"characterOffsetEnd":2060,"pos":"-RRB-","before":"","after":""}]},{"index":18,"tokens":[{"index":1,"word":"All","originalText":"All","characterOffsetBegin":2060,"characterOffsetEnd":2063,"pos":"PDT","before":"","after":" "},{"index":2,"word":"the","originalText":"the","characterOffsetBegin":2064,"characterOffsetEnd":2067,"pos":"DT","before":" ","after":" "},{"index":3,"word":"other","originalText":"other","characterOffsetBegin":2068,"characterOffsetEnd":2073,"pos":"JJ","before":" ","after":" "},{"index":4,"word":"units","originalText":"units","characterOffsetBegin":2074,"characterOffsetEnd":2079,"pos":"NNS","before":" ","after":" "},{"index":5,"word":"were","originalText":"were","characterOffsetBegin":2080,"characterOffsetEnd":2084,"pos":"VBD","before":" ","after":" "},{"index":6,"word":"defined","originalText":"defined","characterOffsetBegin":2085,"characterOffsetEnd":2092,"pos":"VBN","before":" ","after":" "},{"index":7,"word":"many","originalText":"many","characterOffsetBegin":2093,"characterOffsetEnd":2097,"pos":"JJ","before":" ","after":" "},{"index":8,"word":"decades","originalText":"decades","characterOffsetBegin":2098,"characterOffsetEnd":2105,"pos":"NNS","before":" ","after":" "},{"index":9,"word":"earlier","originalText":"earlier","characterOffsetBegin":2106,"characterOffsetEnd":2113,"pos":"RBR","before":" ","after":""},{"index":10,"word":".","originalText":".","characterOffsetBegin":2113,"characterOffsetEnd":2114,"pos":".","before":"","after":" "}]},{"index":19,"tokens":[{"index":1,"word":"--","originalText":"--","characterOffsetBegin":2115,"characterOffsetEnd":2117,"pos":":","before":" ","after":" "},{"index":2,"word":"--------------------------------------------------------------------------------------------------------------------------------------------","originalText":"--------------------------------------------------------------------------------------------------------------------------------------------","characterOffsetBegin":2118,"characterOffsetEnd":2258,"pos":"CD","before":" ","after":""}]}]}